Workbook

Sheet Ejemplo desarrollo sprints
B1: Sprint 1 | C1: Sprint 2 | D1: Sprint 3 | E1: Sprint 4
A2: Sprint 1 | B2: Refinamiento HU | C2: Ejecutar Sprint
A3: Sprint 2 | B3: Redacción HU | C3: Refinamiento HU | D3: Ejecutar Sprint
A4: Sprint 3 | B4: Redacción HU | C4: Refinamiento HU | D4: Ejecutar Sprint
A5: Sprint 4 | B5: Redacción HU | C5: Refinamiento HU | D5: Ejecutar Sprint

Sheet Product Backlog HUs
A1: Identificador | B1: Nombre Comando/Acción | C1: Nombre Historia | D1: Nombre Historia de Usuario | E1: ¿Quién dispara o ejecuta la Historia? | F1: ¿Qué necesita poder llevar a cabo? | G1: ¿Para qué necesita llevar a cabo esa acción? | H1: Card | I1: Talla | J1: Puntos de historia de usuario | K1: ¿Definition of Ready? | L1: ¿Definition of Done? | M1: Prioridad
A2: HU1 | B2: Registrar cliente | C2: Registrar informacion de un nuevo cliente | D2: =A2&"-"&C2 -> HU1-Registrar informacion de un nuevo cliente | E2: Cliente | F2: poder registrar mi información | G2: el administrador tener acceso a la información veraz y actualizada de los clientes que hacen parte de CotiOnline | H2: ="Como "&E2&", necesito "&F2&", para "&G2 -> Como Cliente, necesito poder registrar mi información, para el administrador tener acceso a la información veraz y actualizada de los clientes que hacen parte de CotiOnline | I2: M | J2: 3 | K2: NO | L2: NO | M2: 8
A3: HU2 | B3: Editar info del cliente | C3: Editar información de un cliente existente | D3: =A3&"-"&C3 -> HU2-Editar información de un cliente existente | E3: Cliente | F3: necesito editar la información de mi cuenta existente | G3: con el fin de modificar dicha información y mantener actualizados mis datos | H3: ="Como "&E3&", "&F3&", "&G3 -> Como Cliente, necesito editar la información de mi cuenta existente, con el fin de modificar dicha información y mantener actualizados mis datos | I3: M | J3: 3 | K3: NO | L3: NO | M3: 7
A4: HU3 | B4: Consultar info del cliente | C4: Consultar la información y existencia de un cliente existente | D4: =A4&"-"&C4 -> HU3-Consultar la información y existencia de un cliente existente | E4: Administrador del Sistema | F4: necesito poder consultar la información y existencia de uno o más clientes segun el criterio especificado | G4: con el fin de verificar que un cliente exista o no en la plataforma y al mismo tiempo tener acceso a la información de cada uno de los clientes que hacen parte de CotiOnline | H4: ="Como "&E4&", "&F4&", "&G4 -> Como Administrador del Sistema, necesito poder consultar la información y existencia de uno o más clientes segun el criterio especificado, con el fin de verificar que un cliente exista o no en la plataforma y al mismo tiempo tener acceso a la información de cada uno de los clientes que hacen parte de CotiOnline | I4: S | J4: 2 | K4: NO | L4: NO | M4: 3
A5: HU4 | B5: Cambiar contraseña | C5: Reestablecer/cambiar contraseña de un cliente existente | D5: =A5&"-"&C5 -> HU4-Reestablecer/cambiar contraseña de un cliente existente | E5: Cliente | F5: necesito poder reestablecer la contraseña de mi cuenta | G5: con el fin de brindar facilidad en el cambio de las creedenciales ya sea por seguridad o por olvidar las mismas | H5: ="Como "&E5&", "&F5&", "&G5 -> Como Cliente, necesito poder reestablecer la contraseña de mi cuenta, con el fin de brindar facilidad en el cambio de las creedenciales ya sea por seguridad o por olvidar las mismas | I5: L | J5: 5 | K5: NO | L5: NO | M5: 6
A6: HU5 | B6: Dar de baja cliente | C6: Dar de baja un cliente existente | D6: =A6&"-"&C6 -> HU5-Dar de baja un cliente existente | E6: Administrador del Sistema | F6: necesito poder dar de baja a un cliente existente en la aplicación | G6: con el fin de eliminar del sistema clientes que ya no forman parte de CotiOnline y asi mantener los datos actualizados | H6: ="Como "&E6&", "&F6&", "&G6 -> Como Administrador del Sistema, necesito poder dar de baja a un cliente existente en la aplicación, con el fin de eliminar del sistema clientes que ya no forman parte de CotiOnline y asi mantener los datos actualizados | I6: M | J6: 3 | K6: NO | L6: NO | M6: 3
A7: HU6 | B7: Registrar negocio | C7: Registrar información de un nuevo negocio | D7: =A7&"-"&C7 -> HU6-Registrar información de un nuevo negocio | E7: Cliente | F7: poder registrar la información y documentación de un nuevo negocio | G7: con el fin de tener acceso a la información veraz y actualizada de cada uno de los negocios que pertenecen a los clientes que hacen parte de CotiOnline | H7: ="Como "&E7&", "&F7&", "&G7 -> Como Cliente, poder registrar la información y documentación de un nuevo negocio , con el fin de tener acceso a la información veraz y actualizada de cada uno de los negocios que pertenecen a los clientes que hacen parte de CotiOnline | I7: L | J7: 5 | K7: NO | L7: NO | M7: 9
A8: HU7 | B8: Crear solicitud de cotización | C8: Crear nueva solicitud de cotización | D8: =A8&"-"&C8 -> HU7-Crear nueva solicitud de cotización | E8: Cliente | F8: necesito poder crear una nueva solicitud de cotización | G8: con el fin de solicitar la cotización de productos a los proveedores, conocer y comparar sus precios y adquirir dichos productos | H8: ="Como "&E8&", "&F8&", "&G8 -> Como Cliente, necesito poder crear una nueva solicitud de cotización, con el fin de solicitar la cotización de productos a los proveedores, conocer y comparar sus precios y adquirir dichos productos | I8: XL | J8: 7 | K8: NO | L8: NO | M8: 10
A9: HU8 | B9: Invitar a colaborador | C9: Invitar a un colaborador | D9: =A9&"-"&C9 -> HU8-Invitar a un colaborador | E9: Cliente | F9: necesito poder invitar a un colaborador a la aplicación | G9: con el fin de solicitar apoyo para el analisis y la toma de decisiones frente a las cotizaciones que envian los proveedores | H9: ="Como "&E9&", "&F9&", "&G9 -> Como Cliente, necesito poder invitar a un colaborador a la aplicación, con el fin de solicitar apoyo para el analisis y la toma de decisiones frente a las cotizaciones que envian los proveedores | I9: S | J9: 2 | K9: NO | L9: NO | M9: 2
A10: HU9 | B10: Iniciar sesión | C10: Iniciar sesión en la aplicación | D10: =A10&"-"&C10 -> HU9-Iniciar sesión en la aplicación | E10: Cliente | F10: necesito poder acceder a la aplicación con mis credenciales ya registradas en el sistema | G10: con el fin de acceder a todas las funcionalidades de la aplicación de manera segura y confiable | H10: ="Como "&E10&", "&F10&", "&G10 -> Como Cliente, necesito poder acceder a la aplicación con mis credenciales ya registradas en el sistema, con el fin de acceder a todas las funcionalidades de la aplicación de manera segura y confiable | I10: M | J10: 4 | K10: NO | L10: NO | M10: 6
A11: HU10 | B11: Adquirir plan de suscripción | C11: Adquirir un nuevo plan de suscripción | D11: =A11&"-"&C11 -> HU10-Adquirir un nuevo plan de suscripción | E11: Cliente | F11: necesito poder adquirir un nuevo plan de suscripcion | G11: con el fin de adquirir nuevas funcionalidades para mi negocio dentro de la aplicacion | H11: ="Como "&E11&", "&F11&", "&G11 -> Como Cliente, necesito poder adquirir un nuevo plan de suscripcion, con el fin de adquirir nuevas funcionalidades para mi negocio dentro de la aplicacion | I11: M | J11: 4 | K11: NO | L11: NO | M11: 5
A12: HU11 | B12: Duplicar solicitud de cotizacion | C12: Duplicar y/o clonar una solicitud de cotización | D12: =A12&"-"&C12 -> HU11-Duplicar y/o clonar una solicitud de cotización | E12: Cliente | F12: necesito poder generar una copia exacta de una solicitud de cotización existente | G12: con el fin de reutilizar la información sin tener que llenarla nuevamente | H12: ="Como "&E12&", "&F12&", "&G12 -> Como Cliente, necesito poder generar una copia exacta de una solicitud de cotización existente, con el fin de reutilizar la información sin tener que llenarla nuevamente | I12: S | J12: 2 | K12: NO | L12: NO | M12: 3
A13: HU12 | B13: Editar solicitud de cotizacion | C13: Editar solicitud de cotización existente | D13: =A13&"-"&C13 -> HU12-Editar solicitud de cotización existente | E13: Cliente | F13: necesito modificar los datos de una solicitud de cotización ya creada | G13: con el fin de corregir errores o actualizar la información antes de enviarla | H13: ="Como "&E13&", "&F13&", "&G13 -> Como Cliente, necesito modificar los datos de una solicitud de cotización ya creada, con el fin de corregir errores o actualizar la información antes de enviarla | I13: S | J13: 2 | K13: NO | L13: NO | M13: 4
A14: HU13 | B14: Eliminar solicitud de cotizacion | C14: Eliminar solicitud de cotización | D14: HU13-Eliminar solicitud de cotización | E14: Cliente | F14: necesito eliminar una solicitud de cotización que ya no es necesaria | G14: con el fin de mantener el sistema organizado y evitar solicitudes obsoletas | H14: ="Como "&E14&", "&F14&", "&G14 -> Como Cliente, necesito eliminar una solicitud de cotización que ya no es necesaria, con el fin de mantener el sistema organizado y evitar solicitudes obsoletas | I14: S | J14: 2 | K14: NO | L14: NO | M14: 3
A15: HU14 | B15: Consultar solicitud de cotizacion | C15: Consultar solicitud de cotización | D15: HU14-Consultar solicitud de cotización | E15: Cliente | F15: necesito visualizar el estado y detalles de una solicitud de cotización enviada | G15: con el fin de hacer seguimiento y tomar decisiones en base a la información disponible | H15: ="Como "&E15&", "&F15&", "&G15 -> Como Cliente, necesito visualizar el estado y detalles de una solicitud de cotización enviada, con el fin de hacer seguimiento y tomar decisiones en base a la información disponible | I15: M | J15: 3 | K15: NO | L15: NO | M15: 5
A16: HU15 | B16: Publicar solicitud de cotizacion | C16: Publicar solicitud de cotización | D16: =A16&"-"&C16 -> HU15-Publicar solicitud de cotización | E16: Cliente | F16: necesito hacer visible una solicitud de cotización para los proveedores | G16: con el fin de recibir ofertas y compararlas para seleccionar la mejor opción | H16: ="Como "&E16&", "&F16&", "&G16 -> Como Cliente, necesito hacer visible una solicitud de cotización para los proveedores, con el fin de recibir ofertas y compararlas para seleccionar la mejor opción | I16: M | J16: 3 | K16: NO | L16: NO | M16: 6
A17: HU16 | B17: Aceptar cotizacion | C17: Aceptar cotización | D17: =A17&"-"&C17 -> HU16-Aceptar cotización | E17: Cliente | F17: necesito aprobar una cotización enviada por un proveedor | G17: con el fin de proceder con la compra del producto o servicio cotizado | H17: ="Como "&E17&", "&F17&", "&G17 -> Como Cliente, necesito aprobar una cotización enviada por un proveedor, con el fin de proceder con la compra del producto o servicio cotizado | I17: M | J17: 3 | K17: NO | L17: NO | M17: 6
A18: HU17 | B18: Actualizar estado de cotización | C18: Actualizar estado de cotización | D18: =A18&"-"&C18 -> HU17-Actualizar estado de cotización | E18: Cliente | F18: necesito cambiar el estado de una cotización en función del proceso de compra | G18: con el fin de mantener un seguimiento claro y actualizado de las cotizaciones | H18: ="Como "&E18&", "&F18&", "&G18 -> Como Cliente, necesito cambiar el estado de una cotización en función del proceso de compra, con el fin de mantener un seguimiento claro y actualizado de las cotizaciones | I18: M | J18: 3 | K18: NO | L18: NO | M18: 4
A19: HU18 | B19: Editar información de negocio | C19: Editar información de negocio | D19: =A19&"-"&C19 -> HU18-Editar información de negocio | E19: Cliente | F19: necesito modificar los datos del negocio registrados en la aplicación | G19: con el fin de mantener la información actualizada y evitar inconsistencias | H19: ="Como "&E19&", "&F19&", "&G19 -> Como Cliente, necesito modificar los datos del negocio registrados en la aplicación, con el fin de mantener la información actualizada y evitar inconsistencias | I19: XL | J19: 7 | K19: NO | L19: NO | M19: 7
A20: HU19 | B20: Dar de baja negocio | C20: Dar de baja negocio | D20: =A20&"-"&C20 -> HU19-Dar de baja negocio | E20: Cliente | F20: necesito desactivar o eliminar un negocio registrado en la plataforma | G20: con el fin de gestionar la presencia de negocios activos dentro del sistema | H20: ="Como "&E20&", "&F20&", "&G20 -> Como Cliente, necesito desactivar o eliminar un negocio registrado en la plataforma, con el fin de gestionar la presencia de negocios activos dentro del sistema | I20: L | J20: 5 | K20: NO | L20: NO | M20: 7
A21: HU20 | B21: Crear sede | C21: Crear sede | D21: =A21&"-"&C21 -> HU20-Crear sede | E21: Cliente | F21: necesito registrar una nueva sede para un negocio | G21: con el fin de expandir la cobertura y gestión de operaciones dentro de la aplicación | H21: ="Como "&E21&", "&F21&", "&G21 -> Como Cliente, necesito registrar una nueva sede para un negocio, con el fin de expandir la cobertura y gestión de operaciones dentro de la aplicación | I21: L | J21: 5 | K21: NO | L21: NO | M21: 6
A22: HU21 | B22: Generar notificaciones | C22: Generar notificaciones | D22: =A22&"-"&C22 -> HU21-Generar notificaciones | E22: Cliente | F22: necesito recibir alertas sobre eventos relevantes en la plataforma | G22: con el fin de mantenerse informado sobre actualizaciones y procesos importantes | H22: ="Como "&E22&", "&F22&", "&G22 -> Como Cliente, necesito recibir alertas sobre eventos relevantes en la plataforma, con el fin de mantenerse informado sobre actualizaciones y procesos importantes | I22: L | J22: 5 | K22: NO | L22: NO | M22: 8
A23: HU22 | B23: Generar comparación y analisis de cotizaciones | C23: Generar comparación y análisis de cotizaciones | D23: =A23&"-"&C23 -> HU22-Generar comparación y análisis de cotizaciones | E23: Cliente | F23: necesito analizar diferentes cotizaciones recibidas | G23: con el fin de seleccionar la mejor opción basada en precio y otros criterios | H23: ="Como "&E23&", "&F23&", "&G23 -> Como Cliente, necesito analizar diferentes cotizaciones recibidas, con el fin de seleccionar la mejor opción basada en precio y otros criterios | I23: L | J23: 5 | K23: NO | L23: NO | M23: 9
A24: HU23 | B24: Consultar departamento | C24: Consultar departamento | D24: =A24&"-"&C24 -> HU23-Consultar departamento | E24: Cliente | F24: necesito consultar la lista de departamentos existentes | G24: con el fin de registrar la información de residencia y ubicación del negocio | H24: ="Como "&E24&", "&F24&", "&G24 -> Como Cliente, necesito consultar la lista de departamentos existentes, con el fin de registrar la información de residencia y ubicación del negocio | I24: S | J24: 2 | K24: NO | L24: NO | M24: 3
A25: HU24 | B25: Consultar ciudad | C25: Consultar ciudad | D25: =A25&"-"&C25 -> HU24-Consultar ciudad | E25: Cliente | F25: necesito consultar la lista de ciudades existentes | G25: con el fin de registrar la información de residencia y ubicación del negocio | H25: ="Como "&E25&", "&F25&", "&G25 -> Como Cliente, necesito consultar la lista de ciudades existentes, con el fin de registrar la información de residencia y ubicación del negocio | I25: S | J25: 2 | K25: NO | L25: NO | M25: 3
A26: HU25 | B26: Actualizar sede | C26: Actualizar datos | D26: =A26&"-"&C26 -> HU25-Actualizar datos | E26: Cliente | F26: Necesito actualizar los datos de una sede existente | G26: con el fin de mantener un seguimiento claro y actualizado de las sedes que hacen parte de mi negocio | H26: ="Como "&E26&", "&F26&", "&G26 -> Como Cliente, Necesito actualizar los datos de una sede existente, con el fin de mantener un seguimiento claro y actualizado de las sedes que hacen parte de mi negocio | I26: M | J26: 3 | K26: NO | L26: NO | M26: 4
A27: HU26 | B27: Consultar sede | C27: Consultar sede | D27: =A27&"-"&C27 -> HU26-Consultar sede | E27: Cliente | F27: necesito consultar las sedes que pertenecen a mi negocio | G27: con el fin de ver las sedes que existentes | H27: ="Como "&E27&", "&F27&", "&G27 -> Como Cliente, necesito consultar las sedes que pertenecen a mi negocio, con el fin de ver las sedes que existentes | I27: S | J27: 2 | K27: NO | L27: NO | M27: 2
... A32: HU31 | B32: Eliminar producto | C32: Eliminar producto | D32: =A32&"-"&C32 -> HU31-Eliminar producto | E32: Cliente | F32: necesito eliminar un producto existente | G32: con el fin de descartar los productos innecesarios permitiendo asi una correcta depuración y optimización de la base de datos de la app | H32: ="Como "&E32&", "&F32&", "&G32 -> Como Cliente, necesito eliminar un producto existente, con el fin de descartar los productos innecesarios permitiendo asi una correcta depuración y optimización de la base de datos de la app | I32: S | J32: 2 | K32: NO | L32: NO | M32: 4

Sheet Plan de liberaciones
A1: Historia de usuario | B1: Sprint | C1: Días hábiles | D1: Acumulado días hábiles | E1: Release
A2: ='Product Backlog HUs'!$D$2 -> HU1-Registrar informacion de un nuevo cliente | B2: Sprint 1 | C2: 10 | D2: =C2 -> 10 | E2: Release 1
A3: ='Product Backlog HUs'!$D$3 -> HU2-Editar información de un cliente existente
A4: ='Product Backlog HUs'!$D$4 -> HU3-Consultar la información y existencia de un cliente existente
A5: ='Product Backlog HUs'!$D$6 -> HU5-Dar de baja un cliente existente
A6: ='Product Backlog HUs'!$D$7 -> HU6-Registrar información de un nuevo negocio
A7: ='Product Backlog HUs'!$D$8 -> HU7-Crear nueva solicitud de cotización
A8: ='Product Backlog HUs'!$D$10 -> HU9-Iniciar sesión en la aplicación
A9: ='Product Backlog HUs'!$D$13 -> HU12-Editar solicitud de cotización existente
A10: ='Product Backlog HUs'!$D$14 -> HU13-Eliminar solicitud de cotización
A11: ='Product Backlog HUs'!$D$15 -> HU14-Consultar solicitud de cotización
A12: ='Product Backlog HUs'!$D$19 -> HU18-Editar información de negocio
A13: ='Product Backlog HUs'!$D$20 -> HU19-Dar de baja negocio
A14: ='Product Backlog HUs'!$D$21 -> HU20-Crear sede
A15: ='Product Backlog HUs'!$D$22 -> HU21-Generar notificaciones
A16: ='Product Backlog HUs'!$D$5 -> HU4-Reestablecer/cambiar contraseña de un cliente existente | B16: Sprint 2 | C16: 10 | D16: =D2+C16 -> 20
A17: ='Product Backlog HUs'!$D$16 -> HU15-Publicar solicitud de cotización
A18: ='Product Backlog HUs'!$D$17 -> HU16-Aceptar cotización
A19: ='Product Backlog HUs'!$D$24 -> HU23-Consultar departamento
A20: ='Product Backlog HUs'!$D$25 -> HU24-Consultar ciudad
A21: ='Product Backlog HUs'!$D$9 -> HU8-Invitar a un colaborador | B21: Sprint 3 | C21: 10 | D21: =D16+C21 -> 30 | E21: Release 2
A22: ='Product Backlog HUs'!$D$11 -> HU10-Adquirir un nuevo plan de suscripción
A23: ='Product Backlog HUs'!$D$12 -> HU11-Duplicar y/o clonar una solicitud de cotización
A24: ='Product Backlog HUs'!$D$13 -> HU12-Editar solicitud de cotización existente
A25: ='Product Backlog HUs'!$D$18 -> HU17-Actualizar estado de cotización
A26: (Posible espacio para ajustes) | B26: Sprint 4 | C26: 10 | D26: =D21+C26 -> 40 | E26: Release 3

Sheet Mapa de historias de usuario
A1: Mapa de historias de usuario
B2: Épica 1 | C2: Épica 2 | D2: Épica 3 | E2: Épica 4
A3: Release 1 | B3: ='Product Backlog HUs'!$D$2 -> HU1-Registrar informacion de un nuevo cliente | C3: ='Product Backlog HUs'!$D$7 -> HU6-Registrar información de un nuevo negocio | D3: ='Product Backlog HUs'!$D$8 -> HU7-Crear nueva solicitud de cotización | E3: ='Product Backlog HUs'!$D$10 -> HU9-Iniciar sesión en la aplicación
B4: ='Product Backlog HUs'!$D$3 -> HU2-Editar información de un cliente existente | C4: ='Product Backlog HUs'!$D$19 -> HU18-Editar información de negocio | D4: ='Product Backlog HUs'!$D$13 -> HU12-Editar solicitud de cotización existente | E4: ='Product Backlog HUs'!$D$22 -> HU21-Generar notificaciones
B5: ='Product Backlog HUs'!$D$6 -> HU5-Dar de baja un cliente existente | C5: ='Product Backlog HUs'!$D$20 -> HU19-Dar de baja negocio | D5: ='Product Backlog HUs'!$D$14 -> HU13-Eliminar solicitud de cotización
B6: ='Product Backlog HUs'!$D$4 -> HU3-Consultar la información y existencia de un cliente existente | C6: ='Product Backlog HUs'!$D$21 -> HU20-Crear sede | D6: ='Product Backlog HUs'!$D$15 -> HU14-Consultar solicitud de cotización
A7: Release 2 | B7: ='Product Backlog HUs'!$D$5 -> HU4-Reestablecer/cambiar contraseña de un cliente existente | C7: ='Product Backlog HUs'!$D$24 -> HU23-Consultar departamento | D7: ='Product Backlog HUs'!$D$16 -> HU15-Publicar solicitud de cotización | E7: ='Product Backlog HUs'!$D$26 -> HU25-Actualizar datos
C8: ='Product Backlog HUs'!$D$25 -> HU24-Consultar ciudad | D8: ='Product Backlog HUs'!$D$17 -> HU16-Aceptar cotización | E8: ='Product Backlog HUs'!$D$27 -> HU26-Consultar sede
A9: Release 3 | D9: ='Product Backlog HUs'!$D$9 -> HU8-Invitar a un colaborador | E9: ='Product Backlog HUs'!$D$28 -> HU27-Eliminar sede
D10: ='Product Backlog HUs'!$D$11 -> HU10-Adquirir un nuevo plan de suscripción | E10: ='Product Backlog HUs'!$D$29 -> HU28-Crear producto
D11: ='Product Backlog HUs'!$D$12 -> HU11-Duplicar y/o clonar una solicitud de cotización | E11: ='Product Backlog HUs'!$D$30 -> HU29-Editar producto
D12: ='Product Backlog HUs'!$D$13 -> HU12-Editar solicitud de cotización existente | E12: ='Product Backlog HUs'!$D$31 -> HU30-Consultar producto
D13: ='Product Backlog HUs'!$D$18 -> HU17-Actualizar estado de cotización | E13: ='Product Backlog HUs'!$D$32 -> HU31-Eliminar producto

Sheet HU1
A1: <-Volver al listado
A2: Título
A3: ='Product Backlog HUs'!D2 -> HU1-Registrar informacion de un nuevo cliente
A4: Tarjeta
A5: Como | B5: ='Product Backlog HUs'!$E$2 -> Cliente
A6: Necesito | B6: ='Product Backlog HUs'!$F$2 -> poder registrar mi información
A7: Para | B7: ='Product Backlog HUs'!$G$2 -> el administrador tener acceso a la información veraz y actualizada de los clientes que hacen parte de CotiOnline
A8: ='Product Backlog HUs'!$H$2 -> Como Cliente, necesito poder registrar mi información, para el administrador tener acceso a la información veraz y actualizada de los clientes que hacen parte de CotiOnline
A9: Tallaje
A10: ='Product Backlog HUs'!$I$1 -> Talla | E10: ='Product Backlog HUs'!$I$2 -> M
A11: ='Product Backlog HUs'!$J$1 -> Puntos de historia de usuario | E11: ='Product Backlog HUs'!$J$2 -> 3
A12: ='Product Backlog HUs'!$K$1 -> ¿Definition of Ready? | E12: ='Product Backlog HUs'!$K$2 -> NO
A13: ='Product Backlog HUs'!$L$1 -> ¿Definition of Done? | E13: ='Product Backlog HUs'!$L$2 -> NO
A14: Conversación historia
A15: Requisito de información: | E15: (id, nombre, apellido, correo, contraseña, ciudad)
A16: Prototipo: | E16: HU1 - REGISTRAR USUARIO.jpg
A17: Catálogo de mensajes: | E17: Catálogo de mensajes.xlsx
A18: Catálogo de parámetros: | E18: Catálogo de parámetros.xlsx
A19: Restricciones de diseño: | E19: <Nombre y enlace al documento de restricciones de diseño que aplican para la HU en especial>
A20: * Deben tenerse en cuenta los campos descritos en el requisito de información que no deben ser visibles por el usuario.
A21: * Al momento de hacer la validación de una asociación previamente registrada con el mismo nombre, se validará contenido, más no temas de mayúsculas y minúsculas.
A22: * Otros aspectos de aclaración de interés para el cumplimiento de la HU.
A23: Conversación aspectos generales y transversales
A24: Aspectos generales: | E24: <Nombre y enlace a documento con listado de aspectos generales que aplican para todas las HU>
A25: Criterios aceptación
A26: Código | B26: Escenario | G26: Estado | I26: Observación
G27: Aceptado | H27: No aceptado
A28: CA1 | B28: Dado que un Cliente quiere llevar a cabo su registro de nuevo cliente, cuando ingrese todos los datos de forma correcta, ejecute la acción definida para registrar y el cliente no ha sido previamente registrado, entonces se persiste la información del nuevo cliente, se actualiza la lista de resultados con la información del nuevo cliente, se limpia el formulario de ingreso de datos y se muestra al usuario un mensaje de éxito (GEN_USU_EXI_00001), indicando que el cliente se ha registrado de forma satisfactoria.
A29: CA2 | B29: Dado que un Cliente quiere llevar a cabo su registro de nuevo cliente, cuando ingrese alguno de los datos de forma incorrecta, incumpliendo alguna de las reglas especificadas en el requisito de información y ejecute la acción definida para registrar, entonces se muestran los mensajes de error respectivos al usuario (Problemas de obligatoriedad: GEN_USU_ERR_00003, Problemas de formato: GEN_USU_ERR_00004, Problemas de longitud: GEN_USU_ERR_00005, Problemas de rango: GEN_USU_ERR_00006), indicando cuál fue el problema presentado y cómo puede remediarlo.
A30: CA3 | B30: Dado que un Cliente quiere llevar a cabo su registro de nuevo cliente, cuando ingrese todos los datos de forma correcta, ejecute la acción definida para registrar y exista un cliente previamente registrado con el mismo documento, entonces se limpia el formulario de ingreso de datos y se muestra al usuario un mensaje de error (GEN_USU_ERR_00002), indicando que el cliente que intenta registrar ya existe.
A31: CA4 | B31: Dado que un Cliente quiere llevar a cabo su registro de nuevo cliente, cuando haya ingresado información en un campo determinado del formulario de forma incorrecta, incumpliendo alguna de las reglas especificadas en el requisito de información, y pierda el foco de este, entonces se procede con la validación respectiva y se muestren los mensajes de error respectivos al usuario (Problemas de obligatoriedad: GEN_USU_ERR_00003, Problemas de formato: GEN_USU_ERR_00004, Problemas de longitud: GEN_USU_ERR_00005, Problemas de rango: GEN_USU_ERR_00006), indicando cuál fue el problema presentado y cómo puede remediarlo.

Sheet HU2
A1: <-Volver al listado
A2: Título
A3: ='Product Backlog HUs'!D3 -> HU2-Editar información de un cliente existente
A4: Tarjeta
A5: Como | B5: ='Product Backlog HUs'!$E$3 -> Cliente
A6: Necesito | B6: ='Product Backlog HUs'!$F$3 -> necesito editar la información de mi cuenta existente
A7: Para | B7: ='Product Backlog HUs'!$G$3 -> con el fin de modificar dicha información y mantener actualizados mis datos
A8: ='Product Backlog HUs'!$H$3 -> Como Cliente, necesito editar la información de mi cuenta existente, con el fin de modificar dicha información y mantener actualizados mis datos
A9: Tallaje
A10: ='Product Backlog HUs'!$I$1 -> Talla | E10: ='Product Backlog HUs'!$I$3 -> M
A11: ='Product Backlog HUs'!$J$1 -> Puntos de historia de usuario | E11: ='Product Backlog HUs'!$J$3 -> 3
A12: ='Product Backlog HUs'!$K$1 -> ¿Definition of Ready? | E12: ='Product Backlog HUs'!$K$3 -> NO
A13: ='Product Backlog HUs'!$L$1 -> ¿Definition of Done? | E13: ='Product Backlog HUs'!$L$3 -> NO
A14: Conversación historia
A15: Requisito de información: | E15: (id, nombre, apellido, correo, contraseña, ciudad)
A16: Prototipo: | E16: HU2 - EDITAR INFORMACION.jpg
A17: Catálogo de mensajes: | E17: Catálogo de mensajes.xlsx
A18: Catálogo de parámetros: | E18: Catálogo de parámetros.xlsx
A19: Restricciones de diseño: | E19: <Nombre y enlace al documento de restricciones de diseño que aplican para la HU en especial>
A20: * Deben tenerse en cuenta los campos descritos en el requisito de información que no deben ser visibles por el usuario.
A21: * Al momento de hacer la validación de una asociación previamente registrada con el mismo nombre, se validará contenido, más no temas de mayúsculas y minúsculas.
A22: * Otros aspectos de aclaración de interés para el cumplimiento de la HU.
A23: Conversación aspectos generales y transversales
A24: Aspectos generales: | E24: <Nombre y enlace a documento con listado de aspectos generales que aplican para todas las HU>
A25: Criterios aceptación
A26: Código | B26: Escenario | G26: Estado | I26: Observación
G27: Aceptado | H27: No aceptado
A28: CA1 | B28: Dado que un cliente ingresa a la sección de edición de perfil, cuando modifique los campos como nombre, apellidos, correo, telefono y guarda los cambios, entonces el sistema actualiza los datos del cliente, limpia el formulario y se muestra al usuario un mensaje de éxito (GEN_USU_EXI_00001), indicando que se ha actualizado la información del cliente de manera exitosa
A29: CA2 | B29: Dado que el cliente intenta guardar cambios sin completar campos obligatorios (como el nombre o correo electrónico), cuando Cuando hace clic en "Guardar", entonces se muestra un mensaje de error(GEN_USU_ERR_00002), indicando los campos obligatorios faltantes.
A30: CA3 | B30: Dado que el cliente llena el campo de correo electrónico o número telefónico en un formato incorrecto, cuando intente guardar los cambios, entonces se limpia el formulario de actualización de datos y se muestra al usuario un mensaje de error (GEN_USU_ERR_00003), indicando el formato correcto del campo del formulario.
A31: CA4 | B31: Dado que el cliente ingresa en el campo de correo en el formulario cambiandolo por un correo ya existente en la base de datos de la aplicación, cuando intente guardar los cambios, entonces se limpia el formulario de actualización de datos y se muestra al usuario un mensaje de error (GEN_USU_ERR_00004), indicando que el correo ingresado ya existe en el sistema.

Sheet HU3
A1: <-Volver al listado
A2: Título
A3: ='Product Backlog HUs'!D4 -> HU3-Consultar la información y existencia de un cliente existente
A4: Tarjeta
A5: Como | B5: ='Product Backlog HUs'!$E$4 -> Administrador del Sistema
A6: Necesito | B6: ='Product Backlog HUs'!$F$4 -> necesito poder consultar la información y existencia de uno o más clientes segun el criterio especificado
A7: Para | B7: ='Product Backlog HUs'!$G$4 -> con el fin de verificar que un cliente exista o no en la plataforma y al mismo tiempo tener acceso a la información de cada uno de los clientes que hacen parte de CotiOnline
A8: ='Product Backlog HUs'!$H$4 -> Como Administrador del Sistema, necesito poder consultar la información y existencia de uno o más clientes segun el criterio especificado, con el fin de verificar que un cliente exista o no en la plataforma y al mismo tiempo tener acceso a la información de cada uno de los clientes que hacen parte de CotiOnline
A9: Tallaje
A10: ='Product Backlog HUs'!$I$1 -> Talla | E10: ='Product Backlog HUs'!$I$4 -> S
A11: ='Product Backlog HUs'!$J$1 -> Puntos de historia de usuario | E11: ='Product Backlog HUs'!$J$4 -> 2
A12: ='Product Backlog HUs'!$K$1 -> ¿Definition of Ready? | E12: ='Product Backlog HUs'!$K$4 -> NO
A13: ='Product Backlog HUs'!$L$1 -> ¿Definition of Done? | E13: ='Product Backlog HUs'!$L$4 -> NO
A14: Conversación historia
A15: Requisito de información: | E15: (id, nombre, apellido, correo, ciudad)
A16: Prototipo: | E16: <Nombre y enlace a prototipo de registro de una Asociación>
A17: Catálogo de mensajes: | E17: Catálogo de mensajes.xlsx
A18: Catálogo de parámetros: | E18: Catálogo de parámetros.xlsx
A19: Restricciones de diseño: | E19: <Nombre y enlace al documento de restricciones de diseño que aplican para la HU en especial>
A20: * Deben tenerse en cuenta los campos descritos en el requisito de información que no deben ser visibles por el usuario.
A21: * Al momento de hacer la validación de una asociación previamente registrada con el mismo nombre, se validará contenido, más no temas de mayúsculas y minúsculas.
A22: * Otros aspectos de aclaración de interés para el cumplimiento de la HU.
A23: Conversación aspectos generales y transversales
A24: Aspectos generales: | E24: <Nombre y enlace a documento con listado de aspectos generales que aplican para todas las HU>
A25: Criterios aceptación
A26: Código | B26: Escenario | G26: Estado | I26: Observación
G27: Aceptado | H27: No aceptado
A28: CA1 | B28: Dado que un Administrador ingresa un criterio de búsqueda válido (nombre, correo, teléfono, etc.), cuando ejecuta la acción de búsqueda, entonces el sistema debe mostrar una lista de clientes que coincidan con el criterio, incluyendo información relevante como nombre, correo electrónico y teléfono.
A29: CA2 | B29: Dado que un Administrador realiza una búsqueda con un criterio que no coincide con ningún cliente registrado, cuando ejecuta la acción de búsqueda, entonces el sistema debe mostrar un mensaje indicando que no se encontraron resultados (GEN_TEC_INF_00002).
A30: CA3 | B30: Dado que un Cliente intenta realizar una búsqueda sin ingresar ningún criterio, cuando ejecuta la acción de búsqueda, entonces el sistema debe mostrar un mensaje de error (GEN_TEC_ERR_00003), indicando que se requiere al menos un criterio de búsqueda.

Sheet HU4
A1: <-Volver al listado
A2: Título
A3: ='Product Backlog HUs'!D5 -> HU4-Reestablecer/cambiar contraseña de un cliente existente
A4: Tarjeta
A5: Como | B5: ='Product Backlog HUs'!$E$5 -> Cliente
A6: Necesito | B6: ='Product Backlog HUs'!$F$5 -> necesito poder reestablecer la contraseña de mi cuenta
A7: Para | B7: ='Product Backlog HUs'!$G$5 -> con el fin de brindar facilidad en el cambio de las creedenciales ya sea por seguridad o por olvidar las mismas
A8: ='Product Backlog HUs'!$H$5 -> Como Cliente, necesito poder reestablecer la contraseña de mi cuenta, con el fin de brindar facilidad en el cambio de las creedenciales ya sea por seguridad o por olvidar las mismas
A9: Tallaje
A10: ='Product Backlog HUs'!$I$1 -> Talla | E10: ='Product Backlog HUs'!$I$5 -> L
A11: ='Product Backlog HUs'!$J$1 -> Puntos de historia de usuario | E11: ='Product Backlog HUs'!$J$5 -> 5
A12: ='Product Backlog HUs'!$K$1 -> ¿Definition of Ready? | E12: ='Product Backlog HUs'!$K$5 -> NO
A13: ='Product Backlog HUs'!$L$1 -> ¿Definition of Done? | E13: ='Product Backlog HUs'!$L$5 -> NO
A14: Conversación historia
A15: Requisito de información: | E15: (correo, contraseña)
A16: Prototipo: | E16: HU4 - CAMBIAR CONTRASEÑA.jpg
A17: Catálogo de mensajes: | E17: Catálogo de mensajes.xlsx
A18: Catálogo de parámetros: | E18: Catálogo de parámetros.xlsx
A19: Restricciones de diseño: | E19: <Nombre y enlace al documento de restricciones de diseño que aplican para la HU en especial>
A20: * Deben tenerse en cuenta los campos descritos en el requisito de información que no deben ser visibles por el usuario.
A21: * Al momento de hacer la validación de una asociación previamente registrada con el mismo nombre, se validará contenido, más no temas de mayúsculas y minúsculas.
A22: * Otros aspectos de aclaración de interés para el cumplimiento de la HU.
A23: Conversación aspectos generales y transversales
A24: Aspectos generales: | E24: <Nombre y enlace a documento con listado de aspectos generales que aplican para todas las HU>
A25: Criterios aceptación
A26: Código | B26: Escenario | G26: Estado | I26: Observación
G27: Aceptado | H27: No aceptado
A28: CA1 | B28: Dado que un Cliente selecciona la opción "Olvidé mi contraseña", cuando ingresa su correo electrónico registrado y hace clic en "Enviar", entonces el sistema debe enviar un correo electrónico con un enlace seguro para reestablecer la contraseña.
A29: CA2 | B29: Dado que un Cliente ingresa un correo electrónico no registrado en el sistema, cuando intenta solicitar el reestablecimiento de contraseña, entonces el sistema debe mostrar un mensaje de error (GEN_USU_INF_00002), indicando que el correo no está asociado a ninguna cuenta.
A30: CA3 | B30: Dado que un Cliente hace clic en el enlace de reestablecimiento de contraseña recibido en su correo electrónico, cuando ingresa una nueva contraseña que cumple con los requisitos de seguridad (mínimo 8 caracteres, incluyendo mayúsculas, minúsculas y números) y confirma la acción, entonces el sistema debe actualizar la contraseña y mostrar un mensaje de éxito (GEN_USU_EXI_00003), confirmando que la contraseña ha sido cambiada correctamente.
A31: CA4 | B31: Dado que un Cliente intenta establecer una nueva contraseña que no cumple con los requisitos de seguridad, cuando intenta guardar la nueva contraseña, entonces el sistema debe mostrar un mensaje de error (GEN_USU_ERR_00004), indicando los requisitos necesarios (mínimo 8 caracteres, incluyendo al menos una mayúscula, una letra minúscula,un número y un caracter especial).
A32: CA5 | B32: Dado que un Cliente intenta usar un enlace de reestablecimiento de contraseña que ha expirado o es inválido, cuando hace clic en el enlace, entonces el sistema debe mostrar un mensaje de error (GEN_USU_ERR_00005), indicando que el enlace no es válido o ha expirado, y debe solicitar un nuevo enlace.

Sheet HU5
A1: <-Volver al listado
A2: Título
A3: ='Product Backlog HUs'!D6 -> HU5-Dar de baja un cliente existente
A4: Tarjeta
A5: Como | B5: ='Product Backlog HUs'!$E$6 -> Administrador del Sistema
A6: Necesito | B6: ='Product Backlog HUs'!$F$6 -> necesito poder dar de baja a un cliente existente en la aplicación
A7: Para | B7: ='Product Backlog HUs'!$G$6 -> con el fin de eliminar del sistema clientes que ya no forman parte de CotiOnline y asi mantener los datos actualizados
A8: ='Product Backlog HUs'!$H$6 -> Como Administrador del Sistema, necesito poder dar de baja a un cliente existente en la aplicación, con el fin de eliminar del sistema clientes que ya no forman parte de CotiOnline y asi mantener los datos actualizados
A9: Tallaje
A10: ='Product Backlog HUs'!$I$1 -> Talla | E10: ='Product Backlog HUs'!$I$6 -> M
A11: ='Product Backlog HUs'!$J$1 -> Puntos de historia de usuario | E11: ='Product Backlog HUs'!$J$6 -> 3
A12: ='Product Backlog HUs'!$K$1 -> ¿Definition of Ready? | E12: ='Product Backlog HUs'!$K$6 -> NO
A13: ='Product Backlog HUs'!$L$1 -> ¿Definition of Done? | E13: ='Product Backlog HUs'!$L$6 -> NO
A14: Conversación historia
A15: Requisito de información: | E15: (Id, nombre y apellido)
A16: Prototipo: | E16: <Nombre y enlace a prototipo de registro de una Asociación>
A17: Catálogo de mensajes: | E17: Catálogo de mensajes.xlsx
A18: Catálogo de parámetros: | E18: Catálogo de parámetros.xlsx
A19: Restricciones de diseño: | E19: <Nombre y enlace al documento de restricciones de diseño que aplican para la HU en especial>
A20: * Deben tenerse en cuenta los campos descritos en el requisito de información que no deben ser visibles por el usuario.
A21: * Al momento de hacer la validación de una asociación previamente registrada con el mismo nombre, se validará contenido, más no temas de mayúsculas y minúsculas.
A22: * Otros aspectos de aclaración de interés para el cumplimiento de la HU.
A23: Conversación aspectos generales y transversales
A24: Aspectos generales: | E24: <Nombre y enlace a documento con listado de aspectos generales que aplican para todas las HU>
A25: Criterios aceptación
A26: Código | B26: Escenario | G26: Estado | I26: Observación
G27: Aceptado | H27: No aceptado
A28: CA1 | B28: Dado que un Administrador del Sistema selecciona un cliente existente en la lista de clientes, cuando elige la opción "Dar de baja" y confirma la acción, entonces el sistema debe marcar al cliente como "inactivo" y mostrar un mensaje de éxito (GEN_TEC_EXI_00001), confirmando que el cliente ha sido dado de baja correctamente.
A29: CA2 | B29: Dado que un Administrador del Sistema intenta dar de baja a un cliente sin confirmar la acción, cuando no confirma la acción de baja, entonces el sistema no debe realizar la baja y debe mantener al cliente en estado "activo".
A30: CA3 | B30: Dado que un Administrador del Sistema necesita buscar un cliente específico para dar de baja, cuando ingresa un criterio de búsqueda (nombre, correo, teléfono, etc.) y selecciona al cliente, entonces el sistema debe mostrar la información del cliente y permitir la opción de dar de baja.
A31: CA4 | B31: Dado que un cliente ha sido dado de baja, cuando el cliente intenta iniciar sesión en la plataforma, entonces el sistema debe mostrar un mensaje de error (GEN_USU_INF_00004), indicando que su cuenta ha sido desactivada.

Sheet HU6
A1: <-Volver al listado
A2: Título
A3: ='Product Backlog HUs'!D7 -> HU6-Registrar información de un nuevo negocio
A4: Tarjeta
A5: Como | B5: ='Product Backlog HUs'!$E$7 -> Cliente
A6: Necesito | B6: ='Product Backlog HUs'!$F$7 -> poder registrar la información y documentación de un nuevo negocio
A7: Para | B7: ='Product Backlog HUs'!$G$7 -> con el fin de tener acceso a la información veraz y actualizada de cada uno de los negocios que pertenecen a los clientes que hacen parte de CotiOnline
A8: ='Product Backlog HUs'!$H$7 -> Como Cliente, poder registrar la información y documentación de un nuevo negocio , con el fin de tener acceso a la información veraz y actualizada de cada uno de los negocios que pertenecen a los clientes que hacen parte de CotiOnline
A9: Tallaje
A10: ='Product Backlog HUs'!$I$1 -> Talla | E10: ='Product Backlog HUs'!$I$7 -> L
A11: ='Product Backlog HUs'!$J$1 -> Puntos de historia de usuario | E11: ='Product Backlog HUs'!$J$7 -> 5
A12: ='Product Backlog HUs'!$K$1 -> ¿Definition of Ready? | E12: ='Product Backlog HUs'!$K$7 -> NO
A13: ='Product Backlog HUs'!$L$1 -> ¿Definition of Done? | E13: ='Product Backlog HUs'!$L$7 -> NO
A14: Conversación historia
A15: Requisito de información: | E15: (cliente, nit, nombre, ciudad, direccion, carga documento)
A16: Prototipo: | E16: HU6 - CREAR NEGOCIO.jpg
A17: Catálogo de mensajes: | E17: Catálogo de mensajes.xlsx
A18: Catálogo de parámetros: | E18: Catálogo de parámetros.xlsx
A19: Restricciones de diseño: | E19: <Nombre y enlace al documento de restricciones de diseño que aplican para la HU en especial>
A20: * Deben tenerse en cuenta los campos descritos en el requisito de información que no deben ser visibles por el usuario.
A21: * Al momento de hacer la validación de una asociación previamente registrada con el mismo nombre, se validará contenido, más no temas de mayúsculas y minúsculas.
A22: * Otros aspectos de aclaración de interés para el cumplimiento de la HU.
A23: Conversación aspectos generales y transversales
A24: Aspectos generales: | E24: <Nombre y enlace a documento con listado de aspectos generales que aplican para todas las HU>
A25: Criterios aceptación
A26: Código | B26: Escenario | G26: Estado | I26: Observación
G27: Aceptado | H27: No aceptado
A28: CA1 | B28: Dado que un Cliente ingresa a la sección de registro de negocios, cuando completa todos los campos obligatorios (nombre del negocio, dirección, tipo de negocio, documento de identificación, etc.) y adjunta la documentación requerida (licencias, permisos, etc.), entonces el sistema debe guardar la información del negocio y mostrar un mensaje de éxito (GEN_USU_EXI_00001), confirmando que el negocio ha sido registrado correctamente.
A29: CA2 | B29: Dado que un Cliente intenta guardar un registro sin completar los campos obligatorios, cuando hace clic en "Guardar", entonces el sistema debe mostrar un mensaje de error (GEN_USU_ERR_00002), indicando los campos faltantes.
A30: CA3 | B30: Dado que un Cliente intenta registrar un negocio sin adjuntar la documentación requerida, cuando intenta guardar el registro, entonces el sistema debe mostrar un mensaje de error (GEN_USU_ERR_00003), indicando que la documentación es obligatoria.
A31: CA4 | B31: Dado que un Cliente intenta registrar un negocio con un nombre o documento de identificación que ya existe en el sistema, cuando intenta guardar el registro, entonces el sistema debe mostrar un mensaje de error (GEN_USU_INF_00004), indicando que el negocio ya está registrado.

Sheet HU7
A1: <-Volver al listado
A2: Título
A3: ='Product Backlog HUs'!D8 -> HU7-Crear nueva solicitud de cotización
A4: Tarjeta
A5: Como | B5: ='Product Backlog HUs'!$E$8 -> Cliente
A6: Necesito | B6: ='Product Backlog HUs'!$F$8 -> necesito poder crear una nueva solicitud de cotización
A7: Para | B7: ='Product Backlog HUs'!$G$8 -> con el fin de solicitar la cotización de productos a los proveedores, conocer y comparar sus precios y adquirir dichos productos
A8: ='Product Backlog HUs'!$H$8 -> Como Cliente, necesito poder crear una nueva solicitud de cotización, con el fin de solicitar la cotización de productos a los proveedores, conocer y comparar sus precios y adquirir dichos productos
A9: Tallaje
A10: ='Product Backlog HUs'!$I$1 -> Talla | E10: ='Product Backlog HUs'!$I$8 -> XL
A11: ='Product Backlog HUs'!$J$1 -> Puntos de historia de usuario | E11: ='Product Backlog HUs'!$J$8 -> 7
A12: ='Product Backlog HUs'!$K$1 -> ¿Definition of Ready? | E12: ='Product Backlog HUs'!$K$8 -> NO
A13: ='Product Backlog HUs'!$L$1 -> ¿Definition of Done? | E13: ='Product Backlog HUs'!$L$8 -> NO
A14: Conversación historia
A15: Requisito de información: | E15: (Cliente, codigo, fecha de creacion, fecha expiracion, estado, sede)
A16: Prototipo: | E16: HU7 - CREAR SOLICITUD DE COTIZACION.jpg
A17: Catálogo de mensajes: | E17: Catálogo de mensajes.xlsx
A18: Catálogo de parámetros: | E18: Catálogo de parámetros.xlsx
A19: Restricciones de diseño: | E19: <Nombre y enlace al documento de restricciones de diseño que aplican para la HU en especial>
A20: * Deben tenerse en cuenta los campos descritos en el requisito de información que no deben ser visibles por el usuario.
A21: * Al momento de hacer la validación de una asociación previamente registrada con el mismo nombre, se validará contenido, más no temas de mayúsculas y minúsculas.
A22: * Otros aspectos de aclaración de interés para el cumplimiento de la HU.
A23: Conversación aspectos generales y transversales
A24: Aspectos generales: | E24: <Nombre y enlace a documento con listado de aspectos generales que aplican para todas las HU>
A25: Criterios aceptación
A26: Código | B26: Escenario | G26: Estado | I26: Observación
G27: Aceptado | H27: No aceptado
A28: CA1 | B28: Dado que un Cliente ingresa a la sección de creación de solicitudes de cotización, cuando completa todos los campos obligatorios (productos solicitados, cantidad, fecha de entrega, etc.) y guarda la solicitud, entonces el sistema debe crear la solicitud de cotización y mostrar un mensaje de éxito (GEN_USU_EXI_00001), confirmando que la solicitud ha sido creada correctamente.
A29: CA2 | B29: Dado que un Cliente intenta guardar una solicitud de cotización sin completar los campos obligatorios, Cuando hace clic en "Guardar", entonces el sistema debe mostrar un mensaje de error (GEN_USU_ERR_00002), indicando los campos faltantes.
A30: CA3 | B30: Dado que un Cliente necesita agregar productos a la solicitud de cotización, cuando selecciona productos de un catálogo o lista y especifica las cantidades requeridas, entonces el sistema debe agregar los productos a la solicitud y habilitar la opción de publicar la solicitud.

Sheet HU8
A1: <-Volver al listado
A2: Título
A3: ='Product Backlog HUs'!D9 -> HU8-Invitar a un colaborador
A4: Tarjeta
A5: Como | B5: ='Product Backlog HUs'!$E$9 -> Cliente
A6: Necesito | B6: ='Product Backlog HUs'!$F$9 -> necesito poder invitar a un colaborador a la aplicación
A7: Para | B7: ='Product Backlog HUs'!$G$9 -> con el fin de solicitar apoyo para el analisis y la toma de decisiones frente a las cotizaciones que envian los proveedores
A8: ='Product Backlog HUs'!$H$9 -> Como Cliente, necesito poder invitar a un colaborador a la aplicación, con el fin de solicitar apoyo para el analisis y la toma de decisiones frente a las cotizaciones que envian los proveedores
A9: Tallaje
A10: ='Product Backlog HUs'!$I$1 -> Talla | E10: ='Product Backlog HUs'!$I$9 -> S
A11: ='Product Backlog HUs'!$J$1 -> Puntos de historia de usuario | E11: ='Product Backlog HUs'!$J$9 -> 2
A12: ='Product Backlog HUs'!$K$1 -> ¿Definition of Ready? | E12: ='Product Backlog HUs'!$K$9 -> NO
A13: ='Product Backlog HUs'!$L$1 -> ¿Definition of Done? | E13: ='Product Backlog HUs'!$L$9 -> NO
A14: Conversación historia
A15: Requisito de información: | E15: (Cliente, identificacion, correo, estado)
A16: Prototipo: | E16: HU8 - INVITAR COLABORADOR.jpg
A17: Catálogo de mensajes: | E17: Catálogo de mensajes.xlsx
A18: Catálogo de parámetros: | E18: Catálogo de parámetros.xlsx
A19: Restricciones de diseño: | E19: <Nombre y enlace al documento de restricciones de diseño que aplican para la HU en especial>
A20: * Deben tenerse en cuenta los campos descritos en el requisito de información que no deben ser visibles por el usuario.
A21: * Al momento de hacer la validación de una asociación previamente registrada con el mismo nombre, se validará contenido, más no temas de mayúsculas y minúsculas.
A22: * Otros aspectos de aclaración de interés para el cumplimiento de la HU.
A23: Conversación aspectos generales y transversales
A24: Aspectos generales: | E24: <Nombre y enlace a documento con listado de aspectos generales que aplican para todas las HU>
A25: Criterios aceptación
A26: Código | B26: Escenario | G26: Estado | I26: Observación
G27: Aceptado | H27: No aceptado
A28: CA1 | B28: Dado que un Cliente ingresa a la sección de gestión de colaboradores, cuando ingresa el correo electrónico del colaborador y hace clic en "Enviar invitación", entonces el sistema debe enviar un correo electrónico de invitación al colaborador y mostrar un mensaje de éxito (GEN_USU_EXI_00001), confirmando que la invitación ha sido enviada.
A29: CA2 | B29: Dado que un Cliente intenta enviar una invitación a un correo electrónico inválido o vacío, cuando hace clic en "Enviar invitación", entonces el sistema debe mostrar un mensaje de error (GEN_USU_ERR_00002), indicando que el correo electrónico es inválido o está vacío.

Sheet HU9
A1: <-Volver al listado
A2: Título
A3: ='Product Backlog HUs'!D10 -> HU9-Iniciar sesión en la aplicación
A4: Tarjeta
A5: Como | B5: ='Product Backlog HUs'!$E$10 -> Cliente
A6: Necesito | B6: ='Product Backlog HUs'!$F$10 -> necesito poder acceder a la aplicación con mis credenciales ya registradas en el sistema
A7: Para | B7: ='Product Backlog HUs'!$G$10 -> con el fin de acceder a todas las funcionalidades de la aplicación de manera segura y confiable
A8: ='Product Backlog HUs'!$H$10 -> Como Cliente, necesito poder acceder a la aplicación con mis credenciales ya registradas en el sistema, con el fin de acceder a todas las funcionalidades de la aplicación de manera segura y confiable
A9: Tallaje
A10: ='Product Backlog HUs'!$I$1 -> Talla | E10: ='Product Backlog HUs'!$I$10 -> M
A11: ='Product Backlog HUs'!$J$1 -> Puntos de historia de usuario | E11: ='Product Backlog HUs'!$J$10 -> 4
A12: ='Product Backlog HUs'!$K$1 -> ¿Definition of Ready? | E12: ='Product Backlog HUs'!$K$10 -> NO
A13: ='Product Backlog HUs'!$L$1 -> ¿Definition of Done? | E13: ='Product Backlog HUs'!$L$10 -> NO
A14: Conversación historia
A15: Requisito de información: | E15: (correo, contraseña)
A16: Prototipo: | E16: HU9 - INICIAR SESION.jpg
A17: Catálogo de mensajes: | E17: Catálogo de mensajes.xlsx
A18: Catálogo de parámetros: | E18: Catálogo de parámetros.xlsx
A19: Restricciones de diseño: | E19: <Nombre y enlace al documento de restricciones de diseño que aplican para la HU en especial>
A20: * Deben tenerse en cuenta los campos descritos en el requisito de información que no deben ser visibles por el usuario.
A21: * Al momento de hacer la validación de una asociación previamente registrada con el mismo nombre, se validará contenido, más no temas de mayúsculas y minúsculas.
A22: * Otros aspectos de aclaración de interés para el cumplimiento de la HU.
A23: Conversación aspectos generales y transversales
A24: Aspectos generales: | E24: <Nombre y enlace a documento con listado de aspectos generales que aplican para todas las HU>
A25: Criterios aceptación
A26: Código | B26: Escenario | G26: Estado | I26: Observación
G27: Aceptado | H27: No aceptado
A28: CA1 | B28: Dado que un Cliente ingresa su correo electrónico y contraseña registrados, cuando hace clic en "Iniciar sesión", entonces el sistema debe validar las credenciales y permitir el acceso a la aplicación, mostrando la página de inicio correspondiente.
A29: CA2 | B29: Dado que un Cliente ingresa un correo electrónico o contraseña incorrectos, cuando intenta iniciar sesión, entonces el sistema debe mostrar un mensaje de error (GEN_USU_ERR_00002), indicando que las credenciales son incorrectas.
A30: CA3 | B30: Dado que un Cliente intenta iniciar sesión con credenciales incorrectas múltiples veces (por ejemplo, 5 intentos), cuando supera el número máximo de intentos permitidos, entonces el sistema debe bloquear la cuenta temporalmente y mostrar el mensaje de error (GEN_USU_ERR_00003).

Sheet HU10
A1: <-Volver al listado
A2: Título
A3: ='Product Backlog HUs'!D11 -> HU10-Adquirir un nuevo plan de suscripción
A4: Tarjeta
A5: Como | B5: ='Product Backlog HUs'!$E$11 -> Cliente
A6: Necesito | B6: ='Product Backlog HUs'!$F$11 -> necesito poder adquirir un nuevo plan de suscripcion
A7: Para | B7: ='Product Backlog HUs'!$G$11 -> con el fin de adquirir nuevas funcionalidades para mi negocio dentro de la aplicacion
A8: ='Product Backlog HUs'!$H$11 -> Como Cliente, necesito poder adquirir un nuevo plan de suscripcion, con el fin de adquirir nuevas funcionalidades para mi negocio dentro de la aplicacion
A9: Tallaje
A10: ='Product Backlog HUs'!$I$1 -> Talla | E10: ='Product Backlog HUs'!$I$11 -> M
A11: ='Product Backlog HUs'!$J$1 -> Puntos de historia de usuario | E11: ='Product Backlog HUs'!$J$11 -> 4
A12: ='Product Backlog HUs'!$K$1 -> ¿Definition of Ready? | E12: ='Product Backlog HUs'!$K$11 -> NO
A13: ='Product Backlog HUs'!$L$1 -> ¿Definition of Done? | E13: ='Product Backlog HUs'!$L$11 -> NO
A14: Conversación historia
A15: Requisito de información: | E15: (Cliente, datos de pago)
A16: Prototipo: | E16: <Nombre y enlace a prototipo de registro de una Asociación>
A17: Catálogo de mensajes: | E17: Catálogo de mensajes.xlsx
A18: Catálogo de parámetros: | E18: Catálogo de parámetros.xlsx
A19: Restricciones de diseño: | E19: <Nombre y enlace al documento de restricciones de diseño que aplican para la HU en especial>
A20: * Deben tenerse en cuenta los campos descritos en el requisito de información que no deben ser visibles por el usuario.
A21: * Al momento de hacer la validación de una asociación previamente registrada con el mismo nombre, se validará contenido, más no temas de mayúsculas y minúsculas.
A22: * Otros aspectos de aclaración de interés para el cumplimiento de la HU.
A23: Conversación aspectos generales y transversales
A24: Aspectos generales: | E24: <Nombre y enlace a documento con listado de aspectos generales que aplican para todas las HU>
A25: Criterios aceptación
A26: Código | B26: Escenario | G26: Estado | I26: Observación
G27: Aceptado | H27: No aceptado
A28: CA1 | B28: Dado que un Cliente ingresa a la sección de planes de suscripción, cuando revisa los planes disponibles, entonces el sistema debe mostrar una lista de planes con sus características, precios y funcionalidades incluidas.
A29: CA2 | B29: Dado que un Cliente ha revisado los planes disponibles, cuando selecciona un plan y hace clic en "Seleccionar", entonces el sistema debe mostrar los detalles del plan seleccionado y las opciones de pago.
A30: CA3 | B30: Dado que un Cliente ha seleccionado un plan de suscripción, cuando ingresa los detalles de pago y confirma la transacción, entonces el sistema debe procesar el pago, activar el nuevo plan y mostrar un mensaje de éxito (GEN_USU_EXI_00001), confirmando que la suscripción ha sido adquirida correctamente.
A31: CA4 | B31: Dado que un Cliente intenta completar el proceso de pago con detalles de pago inválidos o incompletos, cuando intenta confirmar la transacción, entonces el sistema debe mostrar un mensaje de error (GEN_USU_ERR_00002), indicando los problemas con los detalles de pago.

Sheet HU11
A1: <-Volver al listado
A2: Título
A3: ='Product Backlog HUs'!D12 -> HU11-Duplicar y/o clonar una solicitud de cotización
A4: Tarjeta
A5: Como | B5: ='Product Backlog HUs'!$E$12 -> Cliente
A6: Necesito | B6: ='Product Backlog HUs'!$F$12 -> necesito poder generar una copia exacta de una solicitud de cotización existente
A7: Para | B7: ='Product Backlog HUs'!$G$12 -> con el fin de reutilizar la información sin tener que llenarla nuevamente
A8: ='Product Backlog HUs'!$H$12 -> Como Cliente, necesito poder generar una copia exacta de una solicitud de cotización existente, con el fin de reutilizar la información sin tener que llenarla nuevamente
A9: Tallaje
A10: ='Product Backlog HUs'!$I$1 -> Talla | E10: ='Product Backlog HUs'!$I$12 -> S
A11: ='Product Backlog HUs'!$J$1 -> Puntos de historia de usuario | E11: ='Product Backlog HUs'!$J$12 -> 2
A12: ='Product Backlog HUs'!$K$1 -> ¿Definition of Ready? | E12: ='Product Backlog HUs'!$K$12 -> NO
A13: ='Product Backlog HUs'!$L$1 -> ¿Definition of Done? | E13: ='Product Backlog HUs'!$L$12 -> NO
A14: Conversación historia
A15: Requisito de información: | E15: (cliente, codigo)
A16: Prototipo: | E16: <Nombre y enlace a prototipo de registro de una Asociación>
A17: Catálogo de mensajes: | E17: Catálogo de mensajes.xlsx
A18: Catálogo de parámetros: | E18: Catálogo de parámetros.xlsx
A19: Restricciones de diseño: | E19: <Nombre y enlace al documento de restricciones de diseño que aplican para la HU en especial>
A20: * Deben tenerse en cuenta los campos descritos en el requisito de información que no deben ser visibles por el usuario.
A21: * Al momento de hacer la validación de una asociación previamente registrada con el mismo nombre, se validará contenido, más no temas de mayúsculas y minúsculas.
A22: * Otros aspectos de aclaración de interés para el cumplimiento de la HU.
A23: Conversación aspectos generales y transversales
A24: Aspectos generales: | E24: <Nombre y enlace a documento con listado de aspectos generales que aplican para todas las HU>
A25: Criterios aceptación
A26: Código | B26: Escenario | G26: Estado | I26: Observación
G27: Aceptado | H27: No aceptado
A28: CA1 | B28: Dado que un Cliente selecciona una solicitud de cotización existente, cuando hace clic en la opción "Copiar solicitud", entonces el sistema debe generar una copia exacta de la solicitud, incluyendo todos los productos, cantidades, y detalles adicionales.
A29: CA2 | B29: Dado que un Cliente ha generado una copia de una solicitud de cotización, cuando realiza modificaciones en la copia (como cambiar cantidades, agregar o eliminar productos), entonces el sistema debe permitir la edición y guardar los cambios como una nueva solicitud.
A30: CA3 | B30: Dado que un Cliente intenta enviar una copia de solicitud sin completar los campos obligatorios, cuando hace clic en "Enviar", entonces el sistema debe mostrar un mensaje de error (GEN_USU_ERR_00003), indicando los campos faltantes.

Sheet HU12
A1: <-Volver al listado
A2: Título
A3: ='Product Backlog HUs'!D13 -> HU12-Editar solicitud de cotización existente
A4: Tarjeta
A5: Como | B5: ='Product Backlog HUs'!$E$13 -> Cliente
A6: Necesito | B6: ='Product Backlog HUs'!$F$13 -> necesito modificar los datos de una solicitud de cotización ya creada
A7: Para | B7: ='Product Backlog HUs'!$G$2 -> el administrador tener acceso a la información veraz y actualizada de los clientes que hacen parte de CotiOnline
A8: ='Product Backlog HUs'!$H$13 -> Como Cliente, necesito modificar los datos de una solicitud de cotización ya creada, con el fin de corregir errores o actualizar la información antes de enviarla
A9: Tallaje
A10: ='Product Backlog HUs'!$I$1 -> Talla | E10: ='Product Backlog HUs'!$I$13 -> S
A11: ='Product Backlog HUs'!$J$1 -> Puntos de historia de usuario | E11: ='Product Backlog HUs'!$J$13 -> 2
A12: ='Product Backlog HUs'!$K$1 -> ¿Definition of Ready? | E12: ='Product Backlog HUs'!$K$13 -> NO
A13: ='Product Backlog HUs'!$L$1 -> ¿Definition of Done? | E13: ='Product Backlog HUs'!$L$13 -> NO
A14: Conversación historia
A15: Requisito de información: | E15: (fecha de creacion, fecha limite de respuesta, estado de solicitud, cliente, sede)
A16: Prototipo: | E16: HU12 - EDITAR SOLICITUD DE COTIZACION.jpg
A17: Catálogo de mensajes: | E17: Catálogo de mensajes.xlsx
A18: Catálogo de parámetros: | E18: Catálogo de parámetros.xlsx
A19: Restricciones de diseño: | E19: <Nombre y enlace al documento de restricciones de diseño que aplican para la HU en especial>
A20: * Deben tenerse en cuenta los campos descritos en el requisito de información que no deben ser visibles por el usuario.
A21: * Al momento de hacer la validación de una asociación previamente registrada con el mismo nombre, se validará contenido, más no temas de mayúsculas y minúsculas.
A22: * Otros aspectos de aclaración de interés para el cumplimiento de la HU.
A23: Conversación aspectos generales y transversales
A24: Aspectos generales: | E24: <Nombre y enlace a documento con listado de aspectos generales que aplican para todas las HU>
A25: Criterios aceptación
A26: Código | B26: Escenario | G26: Estado | I26: Observación
G27: Aceptado | H27: No aceptado
A28: CA1 | B28: Dado que un Cliente quiere modificar los datos de una solicitud de cotización ya creada, cuando ingrese la información correcta y ejecute la acción definida para actualizar la solicitud, entonces se guardan los cambios en la solicitud de cotización, se muestra un mensaje de éxito (GEN_USU_EXI_00001) y la solicitud queda con la información actualizada.
A29: CA2 | B29: Dado que un Cliente quiere modificar los datos de una solicitud de cotización ya creada, cuando ingrese información incorrecta que incumpla con las reglas establecidas para el registro de la solicitud y ejecute la acción para actualizarla, entonces se muestran mensajes de error específicos indicando el problema detectado (Problemas de obligatoriedad: GEN_USU_ERR_00002, Problemas de formato: GEN_USU_ERR_00003, Problemas de longitud: GEN_USU_ERR_00004 ), informando al usuario cómo corregir los errores.
A30: CA3 | B30: Dado que un Cliente quiere modificar los datos de una solicitud de cotización ya creada, cuando la solicitud ya haya sido enviada y el sistema no permita su edición, entonces se muestra un mensaje de error (GEN_USU_ERR_00005) indicando que la solicitud no puede ser modificada porque ya ha sido enviada.

Sheet HU13
A1: <-Volver al listado
A2: Título
A3: ='Product Backlog HUs'!D14 -> HU13-Eliminar solicitud de cotización
A4: Tarjeta
A5: Como | B5: ='Product Backlog HUs'!$E$14 -> Cliente
A6: Necesito | B6: ='Product Backlog HUs'!$F$14 -> necesito eliminar una solicitud de cotización que ya no es necesaria
A7: Para | B7: ='Product Backlog HUs'!$G$14 -> con el fin de mantener el sistema organizado y evitar solicitudes obsoletas
A8: ='Product Backlog HUs'!$H$14 -> Como Cliente, necesito eliminar una solicitud de cotización que ya no es necesaria, con el fin de mantener el sistema organizado y evitar solicitudes obsoletas
A9: Tallaje
A10: ='Product Backlog HUs'!$I$1 -> Talla | E10: ='Product Backlog HUs'!$I$14 -> S
A11: ='Product Backlog HUs'!$J$1 -> Puntos de historia de usuario | E11: ='Product Backlog HUs'!$J$14 -> 2
A12: ='Product Backlog HUs'!$K$1 -> ¿Definition of Ready? | E12: ='Product Backlog HUs'!$K$14 -> NO
A13: ='Product Backlog HUs'!$L$1 -> ¿Definition of Done? | E13: ='Product Backlog HUs'!$L$14 -> NO
A14: Conversación historia
A15: Requisito de información: | E15: (cliente, codigo)
A16: Prototipo: | E16: HU12 - EDITAR SOLICITUD DE COTIZACION.jpg
A17: Catálogo de mensajes: | E17: Catálogo de mensajes.xlsx
A18: Catálogo de parámetros: | E18: Catálogo de parámetros.xlsx
A19: Restricciones de diseño: | E19: <Nombre y enlace al documento de restricciones de diseño que aplican para la HU en especial>
A20: * Deben tenerse en cuenta los campos descritos en el requisito de información que no deben ser visibles por el usuario.
A21: * Al momento de hacer la validación de una asociación previamente registrada con el mismo nombre, se validará contenido, más no temas de mayúsculas y minúsculas.
A22: * Otros aspectos de aclaración de interés para el cumplimiento de la HU.
A23: Conversación aspectos generales y transversales
A24: Aspectos generales: | E24: <Nombre y enlace a documento con listado de aspectos generales que aplican para todas las HU>
A25: Criterios aceptación
A26: Código | B26: Escenario | G26: Estado | I26: Observación
G27: Aceptado | H27: No aceptado
A28: CA1 | B28: Dado que un Cliente quiere eliminar una solicitud de cotización, cuando seleccione una solicitud válida y confirme la acción de eliminación, entonces la solicitud se elimina del sistema, se actualiza la lista de solicitudes y se muestra un mensaje de éxito (GEN_USU_EXI_00001) indicando que la solicitud ha sido eliminada correctamente.
A29: CA2 | B29: Dado que un Cliente quiere eliminar una solicitud de cotización, cuando intente eliminar una solicitud que ya ha sido enviada y no es posible eliminarla, entonces se muestra un mensaje de error (GEN_USU_ERR_00002) informando al usuario que la solicitud no puede ser eliminada porque ya ha sido procesada.
A30: CA3 | B30: Dado que un Cliente quiere eliminar una solicitud de cotización, cuando intente eliminar una solicitud que ya ha sido eliminada previamente o que no existe en el sistema, entonces se muestra un mensaje de error (GEN_USU_ERR_00003) indicando que la solicitud no se encuentra disponible para su eliminación.

Sheet HU14
A1: <-Volver al listado
A2: Título
A3: ='Product Backlog HUs'!D15 -> HU14-Consultar solicitud de cotización
A4: Tarjeta
A5: Como | B5: ='Product Backlog HUs'!$E$15 -> Cliente
A6: Necesito | B6: ='Product Backlog HUs'!$F$15 -> necesito visualizar el estado y detalles de una solicitud de cotización enviada
A7: Para | B7: ='Product Backlog HUs'!$G$15 -> con el fin de hacer seguimiento y tomar decisiones en base a la información disponible
A8: ='Product Backlog HUs'!$H$15 -> Como Cliente, necesito visualizar el estado y detalles de una solicitud de cotización enviada, con el fin de hacer seguimiento y tomar decisiones en base a la información disponible
A9: Tallaje
A10: ='Product Backlog HUs'!$I$1 -> Talla | E10: ='Product Backlog HUs'!$I$15 -> M
A11: ='Product Backlog HUs'!$J$1 -> Puntos de historia de usuario | E11: ='Product Backlog HUs'!$J$15 -> 3
A12: ='Product Backlog HUs'!$K$1 -> ¿Definition of Ready? | E12: ='Product Backlog HUs'!$K$15 -> NO
A13: ='Product Backlog HUs'!$L$1 -> ¿Definition of Done? | E13: ='Product Backlog HUs'!$L$15 -> NO
A14: Conversación historia
A15: Requisito de información: | E15: (codigo)
A16: Prototipo: | E16: HU14 - CONSULTAR SOLICITUD DE COTIZACION.jpg
A17: Catálogo de mensajes: | E17: Catálogo de mensajes.xlsx
A18: Catálogo de parámetros: | E18: Catálogo de parámetros.xlsx
A19: Restricciones de diseño: | E19: <Nombre y enlace al documento de restricciones de diseño que aplican para la HU en especial>
A20: * Deben tenerse en cuenta los campos descritos en el requisito de información que no deben ser visibles por el usuario.
A21: * Al momento de hacer la validación de una asociación previamente registrada con el mismo nombre, se validará contenido, más no temas de mayúsculas y minúsculas.
A22: * Otros aspectos de aclaración de interés para el cumplimiento de la HU.
A23: Conversación aspectos generales y transversales
A24: Aspectos generales: | E24: <Nombre y enlace a documento con listado de aspectos generales que aplican para todas las HU>
A25: Criterios aceptación
A26: Código | B26: Escenario | G26: Estado | I26: Observación
G27: Aceptado | H27: No aceptado
A28: CA1 | B28: Dado que un Cliente quiere visualizar el estado y detalles de una solicitud de cotización enviada, cuando seleccione una solicitud válida desde la lista de solicitudes enviadas, entonces el sistema muestra los detalles completos de la solicitud, incluyendo su estado actual, productos o servicios solicitados, fecha de creación, respuestas recibidas y cualquier observación relevante, junto con un mensaje de éxito (GEN_USU_EXI_00001) indicando que la información ha sido cargada correctamente.
A29: CA2 | B29: Dado que un Cliente quiere visualizar el estado y detalles de una solicitud de cotización enviada, cuando seleccione una solicitud que no existe o ha sido eliminada previamente, entonces el sistema muestra un mensaje de error (GEN_USU_ERR_00002) indicando que la solicitud no está disponible y no se pueden mostrar sus detalles.
A30: CA3 | B30: Dado que un Cliente quiere visualizar el estado y detalles de una solicitud de cotización enviada, cuando intente acceder a una solicitud que pertenece a otro usuario o sobre la que no tiene permisos, entonces el sistema bloquea el acceso y muestra un mensaje de error (GEN_USU_ERR_00003) indicando que el usuario no tiene autorización para ver esa solicitud.

Sheet HU15
A1: <-Volver al listado
A2: Título
A3: ='Product Backlog HUs'!D16 -> HU15-Publicar solicitud de cotización
A4: Tarjeta
A5: Como | B5: ='Product Backlog HUs'!$E$16 -> Cliente
A6: Necesito | B6: ='Product Backlog HUs'!$F$16 -> necesito hacer visible una solicitud de cotización para los proveedores
A7: Para | B7: ='Product Backlog HUs'!$G$16 -> con el fin de recibir ofertas y compararlas para seleccionar la mejor opción
A8: ='Product Backlog HUs'!$H$16 -> Como Cliente, necesito hacer visible una solicitud de cotización para los proveedores, con el fin de recibir ofertas y compararlas para seleccionar la mejor opción
A9: Tallaje
A10: ='Product Backlog HUs'!$I$1 -> Talla | E10: ='Product Backlog HUs'!$I$16 -> M
A11: ='Product Backlog HUs'!$J$1 -> Puntos de historia de usuario | E11: ='Product Backlog HUs'!$J$16 -> 3
A12: ='Product Backlog HUs'!$K$1 -> ¿Definition of Ready? | E12: ='Product Backlog HUs'!$K$16 -> NO
A13: ='Product Backlog HUs'!$L$1 -> ¿Definition of Done? | E13: ='Product Backlog HUs'!$L$16 -> NO
A14: Conversación historia
A15: Requisito de información: | E15: (cliente, codigo)
A16: Prototipo: | E16: HU7 - CREAR SOLICITUD DE COTIZACION.jpg
A17: Catálogo de mensajes: | E17: Catálogo de mensajes.xlsx
A18: Catálogo de parámetros: | E18: Catálogo de parámetros.xlsx
A19: Restricciones de diseño: | E19: <Nombre y enlace al documento de restricciones de diseño que aplican para la HU en especial>
A20: * Deben tenerse en cuenta los campos descritos en el requisito de información que no deben ser visibles por el usuario.
A21: * Al momento de hacer la validación de una asociación previamente registrada con el mismo nombre, se validará contenido, más no temas de mayúsculas y minúsculas.
A22: * Otros aspectos de aclaración de interés para el cumplimiento de la HU.
A23: Conversación aspectos generales y transversales
A24: Aspectos generales: | E24: <Nombre y enlace a documento con listado de aspectos generales que aplican para todas las HU>
A25: Criterios aceptación
A26: Código | B26: Escenario | G26: Estado | I26: Observación
G27: Aceptado | H27: No aceptado
A28: CA1 | B28: Dado que un Cliente quiere hacer visible una solicitud de cotización, cuando seleccione una solicitud válida y confirme su publicación, entonces el sistema cambia el estado de la solicitud a "Visible para proveedores", notifica a los proveedores disponibles y muestra un mensaje de éxito (GEN_USU_EXI_00001) indicando que la solicitud ha sido publicada correctamente.
A29: CA2 | B29: Dado que un Cliente quiere hacer visible una solicitud de cotización, cuando intente publicar una solicitud que ya ha sido publicada previamente, entonces el sistema muestra un mensaje de advertencia (GEN_USU_ADV_00002) indicando que la solicitud ya es visible para los proveedores y no es necesario repetir la acción.
A30: CA3 | B30: Dado que un Cliente quiere hacer visible una solicitud de cotización, cuando intente publicar una solicitud que no tiene toda la información requerida, entonces el sistema bloquea la acción y muestra un mensaje de error (GEN_USU_ERR_00003) indicando que es necesario completar todos los datos antes de hacerla visible para los proveedores.

Sheet HU16
A1: <-Volver al listado
A2: Título
A3: ='Product Backlog HUs'!D17 -> HU16-Aceptar cotización
A4: Tarjeta
A5: Como | B5: ='Product Backlog HUs'!$E$17 -> Cliente
A6: Necesito | B6: ='Product Backlog HUs'!$F$17 -> necesito aprobar una cotización enviada por un proveedor
A7: Para | B7: ='Product Backlog HUs'!$G$17 -> con el fin de proceder con la compra del producto o servicio cotizado
A8: ='Product Backlog HUs'!$H$17 -> Como Cliente, necesito aprobar una cotización enviada por un proveedor, con el fin de proceder con la compra del producto o servicio cotizado
A9: Tallaje
A10: ='Product Backlog HUs'!$I$1 -> Talla | E10: ='Product Backlog HUs'!$I$17 -> M
A11: ='Product Backlog HUs'!$J$1 -> Puntos de historia de usuario | E11: ='Product Backlog HUs'!$J$17 -> 3
A12: ='Product Backlog HUs'!$K$1 -> ¿Definition of Ready? | E12: ='Product Backlog HUs'!$K$17 -> NO
A13: ='Product Backlog HUs'!$L$1 -> ¿Definition of Done? | E13: ='Product Backlog HUs'!$L$17 -> NO
A14: Conversación historia
A15: Requisito de información: | E15: (cliente, cotizacion)
A16: Prototipo: | E16: HU16 - ACEPTAR COTIZACION.jpg
A17: Catálogo de mensajes: | E17: Catálogo de mensajes.xlsx
A18: Catálogo de parámetros: | E18: Catálogo de parámetros.xlsx
A19: Restricciones de diseño: | E19: <Nombre y enlace al documento de restricciones de diseño que aplican para la HU en especial>
A20: * Deben tenerse en cuenta los campos descritos en el requisito de información que no deben ser visibles por el usuario.
A21: * Al momento de hacer la validación de una asociación previamente registrada con el mismo nombre, se validará contenido, más no temas de mayúsculas y minúsculas.
A22: * Otros aspectos de aclaración de interés para el cumplimiento de la HU.
A23: Conversación aspectos generales y transversales
A24: Aspectos generales: | E24: <Nombre y enlace a documento con listado de aspectos generales que aplican para todas las HU>
A25: Criterios aceptación
A26: Código | B26: Escenario | G26: Estado | I26: Observación
G27: Aceptado | H27: No aceptado
A28: CA1 | B28: Dado que un Cliente quiere aprobar una cotización enviada por un proveedor, cuando seleccione una cotización válida y confirme la aprobación, entonces el sistema cambia el estado de la cotización a "Aprobada", notifica al proveedor sobre la aprobación y muestra un mensaje de éxito (GEN_USU_EXI_00001) indicando que la cotización ha sido aprobada correctamente.
A29: CA2 | B29: Dado que un Cliente quiere aprobar una cotización enviada por un proveedor, cuando intente aprobar una cotización que ya ha sido aprobada previamente, entonces el sistema muestra un mensaje de informacion (GEN_USU_INF_00002) indicando que la cotización ya fue aprobada y no es necesario repetir la acción.
A30: CA3 | B30: Dado que un Cliente quiere aprobar una cotización enviada por un proveedor, cuando intente aprobar una cotización cuyo tiempo de validez ha expirado, entonces el sistema bloquea la acción y muestra un mensaje de error (GEN_USU_ERR_00003) indicando que la cotización ya no es válida y debe solicitarse una nueva.

Sheet HU17
A1: <-Volver al listado
A2: Título
A3: ='Product Backlog HUs'!D18 -> HU17-Actualizar estado de cotización
A4: Tarjeta
A5: Como | B5: ='Product Backlog HUs'!$E$18 -> Cliente
A6: Necesito | B6: ='Product Backlog HUs'!$F$18 -> necesito cambiar el estado de una cotización en función del proceso de compra
A7: Para | B7: ='Product Backlog HUs'!$G$18 -> con el fin de mantener un seguimiento claro y actualizado de las cotizaciones
A8: ='Product Backlog HUs'!$H$18 -> Como Cliente, necesito cambiar el estado de una cotización en función del proceso de compra, con el fin de mantener un seguimiento claro y actualizado de las cotizaciones
A9: Tallaje
A10: ='Product Backlog HUs'!$I$1 -> Talla | E10: ='Product Backlog HUs'!$I$18 -> M
A11: ='Product Backlog HUs'!$J$1 -> Puntos de historia de usuario | E11: ='Product Backlog HUs'!$J$18 -> 3
A12: ='Product Backlog HUs'!$K$1 -> ¿Definition of Ready? | E12: ='Product Backlog HUs'!$K$18 -> NO
A13: ='Product Backlog HUs'!$L$1 -> ¿Definition of Done? | E13: ='Product Backlog HUs'!$L$18 -> NO
A14: Conversación historia
A15: Requisito de información: | E15: (cliente, cotizacion, estado)
A16: Prototipo: | E16: HU16 - ACEPTAR COTIZACION.jpg
A17: Catálogo de mensajes: | E17: Catálogo de mensajes.xlsx
A18: Catálogo de parámetros: | E18: Catálogo de parámetros.xlsx
A19: Restricciones de diseño: | E19: <Nombre y enlace al documento de restricciones de diseño que aplican para la HU en especial>
A20: * Deben tenerse en cuenta los campos descritos en el requisito de información que no deben ser visibles por el usuario.
A21: * Al momento de hacer la validación de una asociación previamente registrada con el mismo nombre, se validará contenido, más no temas de mayúsculas y minúsculas.
A22: * Otros aspectos de aclaración de interés para el cumplimiento de la HU.
A23: Conversación aspectos generales y transversales
A24: Aspectos generales: | E24: <Nombre y enlace a documento con listado de aspectos generales que aplican para todas las HU>
A25: Criterios aceptación
A26: Código | B26: Escenario | G26: Estado | I26: Observación
G27: Aceptado | H27: No aceptado
A28: CA1 | B28: Dado que un Cliente quiere actualizar el estado de una cotización, cuando seleccione una cotización válida y elija un nuevo estado permitido según el proceso de compra, entonces el sistema actualiza el estado de la cotización, registra la modificación en el historial y muestra un mensaje de éxito (GEN_USU_EXI_00001) indicando que el estado ha sido cambiado correctamente.
A29: CA2 | B29: Dado que un Cliente quiere actualizar el estado de una cotización, cuando intente cambiar a un estado que no está permitido según la etapa actual del proceso de compra, entonces el sistema bloquea la acción y muestra un mensaje de error (GEN_USU_ERR_00002) indicando que el cambio de estado no es válido.
A30: CA3 | B30: Dado que un Cliente quiere actualizar el estado de una cotización, cuando seleccione la opción de rechazar una cotización, entonces el sistema cambia el estado a "Rechazada", registra la acción en el historial y notifica al proveedor sobre la decisión.

Sheet HU18
A1: <-Volver al listado
A2: Título
A3: ='Product Backlog HUs'!D19 -> HU18-Editar información de negocio
A4: Tarjeta
A5: Como | B5: ='Product Backlog HUs'!$E$19 -> Cliente
A6: Necesito | B6: ='Product Backlog HUs'!$F$19 -> necesito modificar los datos del negocio registrados en la aplicación
A7: Para | B7: ='Product Backlog HUs'!$G$19 -> con el fin de mantener la información actualizada y evitar inconsistencias
A8: ='Product Backlog HUs'!$H$19 -> Como Cliente, necesito modificar los datos del negocio registrados en la aplicación, con el fin de mantener la información actualizada y evitar inconsistencias
A9: Tallaje
A10: ='Product Backlog HUs'!$I$1 -> Talla | E10: ='Product Backlog HUs'!$I$19 -> XL
A11: ='Product Backlog HUs'!$J$1 -> Puntos de historia de usuario | E11: ='Product Backlog HUs'!$J$19 -> 7
A12: ='Product Backlog HUs'!$K$1 -> ¿Definition of Ready? | E12: ='Product Backlog HUs'!$K$19 -> NO
A13: ='Product Backlog HUs'!$L$1 -> ¿Definition of Done? | E13: ='Product Backlog HUs'!$L$19 -> NO
A14: Conversación historia
A15: Requisito de información: | E15: (nit, nombre, descripcion, direccion, cliente)
A16: Prototipo: | E16: HU18 - EDITAR NEGOCIO.jpg
A17: Catálogo de mensajes: | E17: Catálogo de mensajes.xlsx
A18: Catálogo de parámetros: | E18: Catálogo de parámetros.xlsx
A19: Restricciones de diseño: | E19: <Nombre y enlace al documento de restricciones de diseño que aplican para la HU en especial>
A20: * Deben tenerse en cuenta los campos descritos en el requisito de información que no deben ser visibles por el usuario.
A21: * Al momento de hacer la validación de una asociación previamente registrada con el mismo nombre, se validará contenido, más no temas de mayúsculas y minúsculas.
A22: * Otros aspectos de aclaración de interés para el cumplimiento de la HU.
A23: Conversación aspectos generales y transversales
A24: Aspectos generales: | E24: <Nombre y enlace a documento con listado de aspectos generales que aplican para todas las HU>
A25: Criterios aceptación
A26: Código | B26: Escenario | G26: Estado | I26: Observación
G27: Aceptado | H27: No aceptado
A28: CA1 | B28: Dado que un Cliente quiere actualizar los datos de su negocio, cuando ingrese información válida y guarde los cambios, entonces el sistema actualiza los datos del negocio en la base de datos, registra la modificación en el historial y muestra un mensaje de éxito (GEN_USU_EXI_00001) indicando que la actualización fue realizada correctamente.
A29: CA2 | B29: Dado que un Cliente quiere actualizar los datos de su negocio, cuando ingrese información incompleta o no cumpla con los formatos requeridos (nombre, cantidad, descripción), entonces el sistema bloquea la acción, muestra un mensaje de error (GEN_USU_ERR_00002) y resalta los campos con errores para que sean corregidos.
A30: CA3 | B30: Dado que un Cliente quiere actualizar los datos de su negocio, cuando intente guardar sin realizar ninguna modificación, entonces el sistema no realiza ningún cambio y muestra un mensaje informativo (GEN_USU_ERR_00003) indicando que no se detectaron modificaciones en los datos.

Sheet HU19
A1: <-Volver al listado
A2: Título
A3: ='Product Backlog HUs'!D20 -> HU19-Dar de baja negocio
A4: Tarjeta
A5: Como | B5: ='Product Backlog HUs'!$E$20 -> Cliente
A6: Necesito | B6: ='Product Backlog HUs'!$F$20 -> necesito desactivar o eliminar un negocio registrado en la plataforma
A7: Para | B7: ='Product Backlog HUs'!$G$20 -> con el fin de gestionar la presencia de negocios activos dentro del sistema
A8: ='Product Backlog HUs'!$H$20 -> Como Cliente, necesito desactivar o eliminar un negocio registrado en la plataforma, con el fin de gestionar la presencia de negocios activos dentro del sistema
A9: Tallaje
A10: ='Product Backlog HUs'!$I$1 -> Talla | E10: ='Product Backlog HUs'!$I$20 -> L
A11: ='Product Backlog HUs'!$J$1 -> Puntos de historia de usuario | E11: ='Product Backlog HUs'!$J$20 -> 5
A12: ='Product Backlog HUs'!$K$1 -> ¿Definition of Ready? | E12: ='Product Backlog HUs'!$K$20 -> NO
A13: ='Product Backlog HUs'!$L$1 -> ¿Definition of Done? | E13: ='Product Backlog HUs'!$L$20 -> NO
A14: Conversación historia
A15: Requisito de información: | E15: (cliente, nit)
A16: Prototipo: | E16: <Nombre y enlace a prototipo de registro de una Asociación>
A17: Catálogo de mensajes: | E17: Catálogo de mensajes.xlsx
A18: Catálogo de parámetros: | E18: Catálogo de parámetros.xlsx
A19: Restricciones de diseño: | E19: <Nombre y enlace al documento de restricciones de diseño que aplican para la HU en especial>
A20: * Deben tenerse en cuenta los campos descritos en el requisito de información que no deben ser visibles por el usuario.
A21: * Al momento de hacer la validación de una asociación previamente registrada con el mismo nombre, se validará contenido, más no temas de mayúsculas y minúsculas.
A22: * Otros aspectos de aclaración de interés para el cumplimiento de la HU.
A23: Conversación aspectos generales y transversales
A24: Aspectos generales: | E24: <Nombre y enlace a documento con listado de aspectos generales que aplican para todas las HU>
A25: Criterios aceptación
A26: Código | B26: Escenario | G26: Estado | I26: Observación
G27: Aceptado | H27: No aceptado
A28: CA1 | B28: Dado que un Cliente desea eliminar un negocio registrado, cuando confirme la acción y no existan restricciones que impidan la eliminación, entonces el sistema elimina el negocio de la base de datos, registra la acción en el historial y muestra un mensaje de éxito (GEN_USU_EXI_00001) indicando que el negocio ha sido eliminado correctamente.
A29: CA2 | B29: Dado que un Cliente desea eliminar un negocio registrado, cuando existan solicitudes de cotización, pedidos o transacciones activas asociadas al negocio, entonces el sistema bloquea la eliminación y muestra un mensaje de error (GEN_USU_EXI_00002) indicando que el negocio no puede ser eliminado mientras tenga operaciones pendientes.
A30: CA3 | B30: Dado que un Cliente desea desactivar un negocio en lugar de eliminarlo, cuando seleccione la opción de desactivación y confirme la acción, entonces el sistema cambia el estado del negocio a "Inactivo", lo oculta de las búsquedas y muestra un mensaje de éxito (GEN_USU_ERR_00003) indicando que el negocio ha sido desactivado correctamente.

Sheet HU20
A1: <-Volver al listado
A2: Título
A3: ='Product Backlog HUs'!D21 -> HU20-Crear sede
A4: Tarjeta
A5: Como | B5: ='Product Backlog HUs'!$E$21 -> Cliente
A6: Necesito | B6: ='Product Backlog HUs'!$F$21 -> necesito registrar una nueva sede para un negocio
A7: Para | B7: ='Product Backlog HUs'!$G$21 -> con el fin de expandir la cobertura y gestión de operaciones dentro de la aplicación
A8: ='Product Backlog HUs'!$H$21 -> Como Cliente, necesito registrar una nueva sede para un negocio, con el fin de expandir la cobertura y gestión de operaciones dentro de la aplicación
A9: Tallaje
A10: ='Product Backlog HUs'!$I$1 -> Talla | E10: ='Product Backlog HUs'!$I$21 -> L
A11: ='Product Backlog HUs'!$J$1 -> Puntos de historia de usuario | E11: ='Product Backlog HUs'!$J$21 -> 5
A12: ='Product Backlog HUs'!$K$1 -> ¿Definition of Ready? | E12: ='Product Backlog HUs'!$K$21 -> NO
A13: ='Product Backlog HUs'!$L$1 -> ¿Definition of Done? | E13: ='Product Backlog HUs'!$L$21 -> NO
A14: Conversación historia
A15: Requisito de información: | E15: (id, nombre, ciudad, direccion, negocio)
A16: Prototipo: | E16: HU20 - CREAR SEDE.jpg
A17: Catálogo de mensajes: | E17: Catálogo de mensajes.xlsx
A18: Catálogo de parámetros: | E18: Catálogo de parámetros.xlsx
A19: Restricciones de diseño: | E19: <Nombre y enlace al documento de restricciones de diseño que aplican para la HU en especial>
A20: * Deben tenerse en cuenta los campos descritos en el requisito de información que no deben ser visibles por el usuario.
A21: * Al momento de hacer la validación de una asociación previamente registrada con el mismo nombre, se validará contenido, más no temas de mayúsculas y minúsculas.
A22: * Otros aspectos de aclaración de interés para el cumplimiento de la HU.
A23: Conversación aspectos generales y transversales
A24: Aspectos generales: | E24: <Nombre y enlace a documento con listado de aspectos generales que aplican para todas las HU>
A25: Criterios aceptación
A26: Código | B26: Escenario | G26: Estado | I26: Observación
G27: Aceptado | H27: No aceptado
A28: CA1 | B28: Dado que un Cliente desea registrar una nueva sede, cuando complete correctamente todos los campos requeridos y confirme la acción, entonces el sistema guarda la información, asocia la sede al negocio, muestra un mensaje de éxito (GEN_USU_EXI_00001) y la sucursal queda disponible para su gestión dentro de la aplicación.
A29: CA2 | B29: Dado que un Cliente intenta registrar una nueva sede, cuando deje uno o más campos obligatorios vacíos, entonces el sistema bloquea el registro y muestra un mensaje de error (GEN_USU_ERR_00002) indicando que debe completar los campos requeridos.
A30: CA3 | B30: Dado que un Cliente intenta registrar una nueva sede, cuando ingrese una dirección incorrecta o inexistente, entoncesel sistema muestra un mensaje de error (GEN_USU_ERR_00003) indicando que la dirección no es válida y permite corregirla antes de continuar.

Sheet HU21
A1: <-Volver al listado
A2: Título
A3: ='Product Backlog HUs'!D22 -> HU21-Generar notificaciones
A4: Tarjeta
A5: Como | B5: ='Product Backlog HUs'!$E$22 -> Cliente
A6: Necesito | B6: ='Product Backlog HUs'!$F$22 -> necesito recibir alertas sobre eventos relevantes en la plataforma
A7: Para | B7: ='Product Backlog HUs'!$G$22 -> con el fin de mantenerse informado sobre actualizaciones y procesos importantes
A8: ='Product Backlog HUs'!$H$22 -> Como Cliente, necesito recibir alertas sobre eventos relevantes en la plataforma, con el fin de mantenerse informado sobre actualizaciones y procesos importantes
A9: Tallaje
A10: ='Product Backlog HUs'!$I$1 -> Talla | E10: ='Product Backlog HUs'!$I$22 -> L
A11: ='Product Backlog HUs'!$J$1 -> Puntos de historia de usuario | E11: ='Product Backlog HUs'!$J$22 -> 5
A12: ='Product Backlog HUs'!$K$1 -> ¿Definition of Ready? | E12: ='Product Backlog HUs'!$K$22 -> NO
A13: ='Product Backlog HUs'!$L$1 -> ¿Definition of Done? | E13: ='Product Backlog HUs'!$L$22 -> NO
A14: Conversación historia
A15: Requisito de información: | E15: (id_cotizacion, nuevo_estado, proveedor)
A16: Prototipo: | E16: HU21 - GENERAR NOTIFICACIONES.jpg
A17: Catálogo de mensajes: | E17: Catálogo de mensajes.xlsx
A18: Catálogo de parámetros: | E18: Catálogo de parámetros.xlsx
A19: Restricciones de diseño: | E19: <Nombre y enlace al documento de restricciones de diseño que aplican para la HU en especial>
A20: * Deben tenerse en cuenta los campos descritos en el requisito de información que no deben ser visibles por el usuario.
A21: * Al momento de hacer la validación de una asociación previamente registrada con el mismo nombre, se validará contenido, más no temas de mayúsculas y minúsculas.
A22: * Otros aspectos de aclaración de interés para el cumplimiento de la HU.
A23: Conversación aspectos generales y transversales
A24: Aspectos generales: | E24: <Nombre y enlace a documento con listado de aspectos generales que aplican para todas las HU>
A25: Criterios aceptación
A26: Código | B26: Escenario | G26: Estado | I26: Observación
G27: Aceptado | H27: No aceptado
A28: CA1 | B28: Dado que un Cliente tiene activadas las notificaciones en la aplicación, cuando ocurra un evento relevante (ej. una nueva cotización, una actualización de estado, un mensaje de un proveedor), entonces el sistema envía una alerta por el canal configurado (ej. notificación push, correo electrónico, SMS) y el Cliente puede visualizar la información correspondiente (GEN_USU_INF_00001).
A29: CA2 | B29: Dado que un Cliente tiene las notificaciones desactivadas en su dispositivo o en la configuración de la aplicación, cuandoocurra un evento relevante, entonces el sistema no enviará alertas y el Cliente no recibirá notificaciones hasta que active nuevamente esta opción.

Sheet HU22
A1: <-Volver al listado
A2: Título
A3: ='Product Backlog HUs'!D23 -> HU22-Generar comparación y análisis de cotizaciones
A4: Tarjeta
A5: Como | B5: ='Product Backlog HUs'!$E$23 -> Cliente
A6: Necesito | B6: ='Product Backlog HUs'!$F$23 -> necesito analizar diferentes cotizaciones recibidas
A7: Para | B7: ='Product Backlog HUs'!$G$23 -> con el fin de seleccionar la mejor opción basada en precio y otros criterios
A8: ='Product Backlog HUs'!$H$23 -> Como Cliente, necesito analizar diferentes cotizaciones recibidas, con el fin de seleccionar la mejor opción basada en precio y otros criterios
A9: Tallaje
A10: ='Product Backlog HUs'!$I$1 -> Talla | E10: ='Product Backlog HUs'!$I$23 -> L
A11: ='Product Backlog HUs'!$J$1 -> Puntos de historia de usuario | E11: ='Product Backlog HUs'!$J$23 -> 5
A12: ='Product Backlog HUs'!$K$1 -> ¿Definition of Ready? | E12: ='Product Backlog HUs'!$K$23 -> NO
A13: ='Product Backlog HUs'!$L$1 -> ¿Definition of Done? | E13: ='Product Backlog HUs'!$L$23 -> NO
A14: Conversación historia
A15: Requisito de información: | E15: (cliente, precio, tiempo_entrega)
A16: Prototipo: | E16: HU22 - GENERAR COMPARACION Y ANALISIS.jpg
A17: Catálogo de mensajes: | E17: Catálogo de mensajes.xlsx
A18: Catálogo de parámetros: | E18: Catálogo de parámetros.xlsx
A19: Restricciones de diseño: | E19: <Nombre y enlace al documento de restricciones de diseño que aplican para la HU en especial>
A20: * Deben tenerse en cuenta los campos descritos en el requisito de información que no deben ser visibles por el usuario.
A21: * Al momento de hacer la validación de una asociación previamente registrada con el mismo nombre, se validará contenido, más no temas de mayúsculas y minúsculas.
A22: * Otros aspectos de aclaración de interés para el cumplimiento de la HU.
A23: Conversación aspectos generales y transversales
A24: Aspectos generales: | E24: <Nombre y enlace a documento con listado de aspectos generales que aplican para todas las HU>
A25: Criterios aceptación
A26: Código | B26: Escenario | G26: Estado | I26: Observación
G27: Aceptado | H27: No aceptado
A28: CA1 | B28: Dado que un Cliente ha recibido varias cotizaciones de diferentes proveedores, cuando el Cliente acceda a la sección de cotizaciones en la aplicación, entonces el sistema mostrará todas las cotizaciones recibidas junto con detalles como el precio, tiempo estimado de entrega y otros criterios relevantes para que el Cliente pueda analizarlas.
A29: CA2 | B29: Dado que un Cliente ha recibido varias cotizaciones de diferentes proveedores, cuando el Cliente seleccione una cotización para ver más detalles, entonces el sistema mostrará toda la información relevante de esa cotización (ej. precio, detalles del proveedor, condiciones de pago) para facilitar el análisis y comparación.
A30: CA3 | B30: Dado que un Cliente ha recibido varias cotizaciones, cuando el Cliente utilice los filtros o herramientas de clasificación disponibles en la aplicación, entonces el sistema mostrará las cotizaciones ordenadas según los criterios seleccionados (ej. precio más bajo, tiempo de entrega más rápido).

Sheet HU23
A1: <-Volver al listado
A2: Título
A3: ='Product Backlog HUs'!D24 -> HU23-Consultar departamento
A4: Tarjeta
A5: Como | B5: ='Product Backlog HUs'!$E$24 -> Cliente
A6: Necesito | B6: ='Product Backlog HUs'!$F$24 -> necesito consultar la lista de departamentos existentes
A7: Para | B7: ='Product Backlog HUs'!$G$24 -> con el fin de registrar la información de residencia y ubicación del negocio
A8: ='Product Backlog HUs'!$H$24 -> Como Cliente, necesito consultar la lista de departamentos existentes, con el fin de registrar la información de residencia y ubicación del negocio
A9: Tallaje
A10: ='Product Backlog HUs'!$I$1 -> Talla | E10: ='Product Backlog HUs'!$I$24 -> S
A11: ='Product Backlog HUs'!$J$1 -> Puntos de historia de usuario | E11: ='Product Backlog HUs'!$J$24 -> 2
A12: ='Product Backlog HUs'!$K$1 -> ¿Definition of Ready? | E12: ='Product Backlog HUs'!$K$24 -> NO
A13: ='Product Backlog HUs'!$L$1 -> ¿Definition of Done? | E13: ='Product Backlog HUs'!$L$24 -> NO
A14: Conversación historia
A15: Requisito de información: | E15: (nombre)
A16: Prototipo: | E16: HU20 - CREAR SEDE.jpg
A17: Catálogo de mensajes: | E17: Catálogo de mensajes.xlsx
A18: Catálogo de parámetros: | E18: Catálogo de parámetros.xlsx
A19: Restricciones de diseño: | E19: <Nombre y enlace al documento de restricciones de diseño que aplican para la HU en especial>
A20: * Deben tenerse en cuenta los campos descritos en el requisito de información que no deben ser visibles por el usuario.
A21: * Al momento de hacer la validación de una asociación previamente registrada con el mismo nombre, se validará contenido, más no temas de mayúsculas y minúsculas.
A22: * Otros aspectos de aclaración de interés para el cumplimiento de la HU.
A23: Conversación aspectos generales y transversales
A24: Aspectos generales: | E24: <Nombre y enlace a documento con listado de aspectos generales que aplican para todas las HU>
A25: Criterios aceptación
A26: Código | B26: Escenario | G26: Estado | I26: Observación
G27: Aceptado | H27: No aceptado
A28: CA1 | B28: Dado que un Cliente ingresa a la sección de registro de información personal o del negocio, cuando selecciona la opción para elegir un departamento, entonces el sistema debe mostrar una lista completa de departamentos disponibles.
A29: CA2 | B29: Dado que un Cliente ha consultado la lista de departamentos, cuando selecciona un departamento de la lista, entonces el sistema debe permitir que el departamento seleccionado sea registrado como parte de la información de residencia o ubicación del negocio.
A30: CA3 | B30: Dado que un Cliente necesita encontrar un departamento específico en la lista, cuando ingresa el nombre o parte del nombre del departamento en un campo de búsqueda, entonces el sistema debe filtrar y mostrar solo los departamentos que coincidan con el criterio de búsqueda.
A31: CA4 | B31: Dado que un Cliente intenta guardar la información sin seleccionar un departamento, cuando hace clic en "Guardar", entonces el sistema debe mostrar un mensaje de error (GEN_USU_ERR_00004), indicando que la selección de un departamento es obligatoria.

Sheet HU24
A1: <-Volver al listado
A2: Título
A3: ='Product Backlog HUs'!D25 -> HU24-Consultar ciudad
A4: Tarjeta
A5: Como | B5: ='Product Backlog HUs'!$E$25 -> Cliente
A6: Necesito | B6: ='Product Backlog HUs'!$F$25 -> necesito consultar la lista de ciudades existentes
A7: Para | B7: ='Product Backlog HUs'!$G$25 -> con el fin de registrar la información de residencia y ubicación del negocio
A8: ='Product Backlog HUs'!$H$25 -> Como Cliente, necesito consultar la lista de ciudades existentes, con el fin de registrar la información de residencia y ubicación del negocio
A9: Tallaje
A10: ='Product Backlog HUs'!$I$1 -> Talla | E10: ='Product Backlog HUs'!$I$25 -> S
A11: ='Product Backlog HUs'!$J$1 -> Puntos de historia de usuario | E11: ='Product Backlog HUs'!$J$25 -> 2
A12: ='Product Backlog HUs'!$K$1 -> ¿Definition of Ready? | E12: ='Product Backlog HUs'!$K$25 -> NO
A13: ='Product Backlog HUs'!$L$1 -> ¿Definition of Done? | E13: ='Product Backlog HUs'!$L$25 -> NO
A14: Conversación historia
A15: Requisito de información: | E15: (nombre)
A16: Prototipo: | E16: HU20 - CREAR SEDE.jpg
A17: Catálogo de mensajes: | E17: Catálogo de mensajes.xlsx
A18: Catálogo de parámetros: | E18: Catálogo de parámetros.xlsx
A19: Restricciones de diseño: | E19: <Nombre y enlace al documento de restricciones de diseño que aplican para la HU en especial>
A20: * Deben tenerse en cuenta los campos descritos en el requisito de información que no deben ser visibles por el usuario.
A21: * Al momento de hacer la validación de una asociación previamente registrada con el mismo nombre, se validará contenido, más no temas de mayúsculas y minúsculas.
A22: * Otros aspectos de aclaración de interés para el cumplimiento de la HU.
A23: Conversación aspectos generales y transversales
A24: Aspectos generales: | E24: <Nombre y enlace a documento con listado de aspectos generales que aplican para todas las HU>
A25: Criterios aceptación
A26: Código | B26: Escenario | G26: Estado | I26: Observación
G27: Aceptado | H27: No aceptado
A28: CA1 | B28: Dado que un Cliente ingresa a la sección de registro de información personal o del negocio, cuando selecciona la opción para elegir una ciudad, entonces el sistema debe mostrar una lista completa de ciudades disponibles.
A29: CA2 | B29: Dado que un Cliente ha consultado la lista de ciudades, cuando selecciona una ciudad de la lista, entonces el sistema debe permitir que la ciudad seleccionada sea registrada como parte de la información de residencia o ubicación del negocio.
A30: CA3 | B30: Dado que un Cliente necesita encontrar una ciudad en específico en la lista, cuando ingresa el nombre o parte del nombre de la ciudad en un campo de búsqueda, entonces el sistema debe filtrar y mostrar solo las ciudades que coincidan con el criterio de búsqueda.
A31: CA4 | B31: Dado que un Cliente intenta guardar la información sin seleccionar una ciudad, cuando hace clic en "Guardar", entonces el sistema debe mostrar un mensaje de error (GEN_USU_ERR_00004), indicando que la selección de una ciudad es obligatoria.

Sheet HU25
A1: <-Volver al listado
A2: Título
A3: ='Product Backlog HUs'!D26 -> HU25-Actualizar datos
A4: Tarjeta
A5: Como | B5: ='Product Backlog HUs'!$E$26 -> Cliente
A6: Necesito | B6: ='Product Backlog HUs'!$F$26 -> Necesito actualizar los datos de una sede existente
A7: Para | B7: ='Product Backlog HUs'!$G$26 -> con el fin de mantener un seguimiento claro y actualizado de las sedes que hacen parte de mi negocio
A8: ='Product Backlog HUs'!$H$26 -> Como Cliente, Necesito actualizar los datos de una sede existente, con el fin de mantener un seguimiento claro y actualizado de las sedes que hacen parte de mi negocio
A9: Tallaje
A10: ='Product Backlog HUs'!$I$1 -> Talla | E10: ='Product Backlog HUs'!$I$26 -> M
A11: ='Product Backlog HUs'!$J$1 -> Puntos de historia de usuario | E11: ='Product Backlog HUs'!$J$26 -> 3
A12: ='Product Backlog HUs'!$K$1 -> ¿Definition of Ready? | E12: ='Product Backlog HUs'!$K$26 -> NO
A13: ='Product Backlog HUs'!$L$1 -> ¿Definition of Done? | E13: ='Product Backlog HUs'!$L$26 -> NO
A14: Conversación historia
A15: Requisito de información: | E15: (codigo, negocio)
A16: Prototipo: | E16: HU20 - CREAR SEDE.jpg
A17: Catálogo de mensajes: | E17: Catálogo de mensajes.xlsx
A18: Catálogo de parámetros: | E18: Catálogo de parámetros.xlsx
A19: Restricciones de diseño: | E19: <Nombre y enlace al documento de restricciones de diseño que aplican para la HU en especial>
A20: * Deben tenerse en cuenta los campos descritos en el requisito de información que no deben ser visibles por el usuario.
A21: * Al momento de hacer la validación de una asociación previamente registrada con el mismo nombre, se validará contenido, más no temas de mayúsculas y minúsculas.
A22: * Otros aspectos de aclaración de interés para el cumplimiento de la HU.
A23: Conversación aspectos generales y transversales
A24: Aspectos generales: | E24: <Nombre y enlace a documento con listado de aspectos generales que aplican para todas las HU>
A25: Criterios aceptación
A26: Código | B26: Escenario | G26: Estado | I26: Observación
G27: Aceptado | H27: No aceptado
A28: CA1 | B28: Dado que un Cliente quiere actualizar los datos de una sede, cuando ingrese información válida y guarde los cambios, entonces el sistema actualiza los datos de la sede en la base de datos, registra la modificación en el historial y muestra un mensaje de éxito (GEN_USU_EXI_00001) indicando que la actualización fue realizada correctamente.
A29: CA2 | B29: Dado que un Cliente quiere actualizar los datos de una sede, cuando ingrese información incompleta o no cumpla con los formatos requeridos (nombre, direccion), entonces el sistema bloquea la acción, muestra un mensaje de error (GEN_USU_ERR_00002) y resalta los campos con errores para que sean corregidos.
A30: CA3 | B30: Dado que un Cliente quiere actualizar los datos de una sede, cuando intente guardar sin realizar ninguna modificación, entonces el sistema no realiza ningún cambio y muestra un mensaje informativo (GEN_USU_ERR_00003) indicando que no se detectaron modificaciones en los datos.

Sheet HU26
A1: <-Volver al listado
A2: Título
A3: ='Product Backlog HUs'!D27 -> HU26-Consultar sede
A4: Tarjeta
A5: Como | B5: ='Product Backlog HUs'!$E$27 -> Cliente
A6: Necesito | B6: ='Product Backlog HUs'!$F$27 -> necesito consultar las sedes que pertenecen a mi negocio
A7: Para | B7: ='Product Backlog HUs'!$G$27 -> con el fin de ver las sedes que existentes
A8: ='Product Backlog HUs'!$H$27 -> Como Cliente, necesito consultar las sedes que pertenecen a mi negocio, con el fin de ver las sedes que existentes
A9: Tallaje
A10: ='Product Backlog HUs'!$I$1 -> Talla | E10: ='Product Backlog HUs'!$I$27 -> S
A11: ='Product Backlog HUs'!$J$1 -> Puntos de historia de usuario | E11: ='Product Backlog HUs'!$J$27 -> 2
A12: ='Product Backlog HUs'!$K$1 -> ¿Definition of Ready? | E12: ='Product Backlog HUs'!$K$27 -> NO
A13: ='Product Backlog HUs'!$L$1 -> ¿Definition of Done? | E13: ='Product Backlog HUs'!$L$27 -> NO
A14: Conversación historia
A15: Requisito de información: | E15: (nombre)
A16: Prototipo: | E16: HU26 - CONSULTAR SEDE.jpg
A17: Catálogo de mensajes: | E17: Catálogo de mensajes.xlsx
A18: Catálogo de parámetros: | E18: Catálogo de parámetros.xlsx
A19: Restricciones de diseño: | E19: <Nombre y enlace al documento de restricciones de diseño que aplican para la HU en especial>
A20: * Deben tenerse en cuenta los campos descritos en el requisito de información que no deben ser visibles por el usuario.
A21: * Al momento de hacer la validación de una asociación previamente registrada con el mismo nombre, se validará contenido, más no temas de mayúsculas y minúsculas.
A22: * Otros aspectos de aclaración de interés para el cumplimiento de la HU.
A23: Conversación aspectos generales y transversales
A24: Aspectos generales: | E24: <Nombre y enlace a documento con listado de aspectos generales que aplican para todas las HU>
A25: Criterios aceptación
A26: Código | B26: Escenario | G26: Estado | I26: Observación
G27: Aceptado | H27: No aceptado
A28: CA1 | B28: Dado que un Cliente ingresa a la sección de crear una solicitud de cotización o listar las sedes, cuando selecciona la opción para elegir una sede, entonces el sistema debe mostrar una lista completa de las sedes existentes.
A29: CA2 | B29: Dado que un Cliente ha consultado la lista de sede, cuando selecciona una sede de la lista, entonces el sistema debe permitir que este sea registrada por parte de la solicitud de cotización.
A30: CA3 | B30: Dado que un Cliente necesita encontrar una sede en específico en la lista, cuando ingresa el nombre o parte del nombre de la sede en un campo de búsqueda, entonces el sistema debe filtrar y mostrar solo las sedes que coincidan con el criterio de búsqueda.

Sheet HU27
A1: <-Volver al listado
A2: Título
A3: ='Product Backlog HUs'!D28 -> HU27-Eliminar sede
A4: Tarjeta
A5: Como | B5: ='Product Backlog HUs'!$E$28 -> Cliente
A6: Necesito | B6: ='Product Backlog HUs'!$F$28 -> necesito eliminar una sede existente
A7: Para | B7: ='Product Backlog HUs'!$G$28 -> con el fin de mantener actualizada la información de las sedes vigentes
A8: ='Product Backlog HUs'!$H$28 -> Como Cliente, necesito eliminar una sede existente, con el fin de mantener actualizada la información de las sedes vigentes
A9: Tallaje
A10: ='Product Backlog HUs'!$I$1 -> Talla | E10: ='Product Backlog HUs'!$I$28 -> S
A11: ='Product Backlog HUs'!$J$1 -> Puntos de historia de usuario | E11: ='Product Backlog HUs'!$J$28 -> 2
A12: ='Product Backlog HUs'!$K$1 -> ¿Definition of Ready? | E12: ='Product Backlog HUs'!$K$28 -> NO
A13: ='Product Backlog HUs'!$L$1 -> ¿Definition of Done? | E13: ='Product Backlog HUs'!$L$28 -> NO
A14: Conversación historia
A15: Requisito de información: | E15: (codigo, nombre, negocio)
A16: Prototipo: | E16: <Nombre y enlace a prototipo de registro de una Asociación>
A17: Catálogo de mensajes: | E17: Catálogo de mensajes.xlsx
A18: Catálogo de parámetros: | E18: Catálogo de parámetros.xlsx
A19: Restricciones de diseño: | E19: <Nombre y enlace al documento de restricciones de diseño que aplican para la HU en especial>
A20: * Deben tenerse en cuenta los campos descritos en el requisito de información que no deben ser visibles por el usuario.
A21: * Al momento de hacer la validación de una asociación previamente registrada con el mismo nombre, se validará contenido, más no temas de mayúsculas y minúsculas.
A22: * Otros aspectos de aclaración de interés para el cumplimiento de la HU.
A23: Conversación aspectos generales y transversales
A24: Aspectos generales: | E24: <Nombre y enlace a documento con listado de aspectos generales que aplican para todas las HU>
A25: Criterios aceptación
A26: Código | B26: Escenario | G26: Estado | I26: Observación
G27: Aceptado | H27: No aceptado
A28: CA1 | B28: Dado que un Cliente desea eliminar una sede registrada, cuando confirme la acción y no existan restricciones que impidan la eliminación, entonces el sistema elimina la sede de la base de datos, registra la acción en el historial y muestra un mensaje de éxito (GEN_USU_EXI_00001) indicando que la sede ha sido eliminada correctamente.
A29: CA2 | B29: Dado que un Cliente desea eliminar una sede registrada, cuando existan solicitudes de cotización, pedidos o transacciones activas asociadas a la sede, entonces el sistema bloquea la eliminación y muestra un mensaje de error (GEN_USU_EXI_00002) indicando que la sede no puede ser eliminada mientras tenga operaciones pendientes.

Sheet HU28
A1: <-Volver al listado
A2: Título
A3: ='Product Backlog HUs'!D29 -> HU28-Crear producto
A4: Tarjeta
A5: Como | B5: ='Product Backlog HUs'!$E$29 -> Cliente
A6: Necesito | B6: ='Product Backlog HUs'!$F$29 -> necesito crear un nuevo producto en la aplicación
A7: Para | B7: ='Product Backlog HUs'!$G$29 -> con el fin de estandarizar las caracteristicas de estos, permitiendo realizar una correcta solicitud de cotización a los proveedores
A8: ='Product Backlog HUs'!$H$29 -> Como Cliente, necesito crear un nuevo producto en la aplicación, con el fin de estandarizar las caracteristicas de estos, permitiendo realizar una correcta solicitud de cotización a los proveedores
A9: Tallaje
A10: ='Product Backlog HUs'!$I$1 -> Talla | E10: ='Product Backlog HUs'!$I$29 -> M
A11: ='Product Backlog HUs'!$J$1 -> Puntos de historia de usuario | E11: ='Product Backlog HUs'!$J$29 -> 3
A12: ='Product Backlog HUs'!$K$1 -> ¿Definition of Ready? | E12: ='Product Backlog HUs'!$K$29 -> NO
A13: ='Product Backlog HUs'!$L$1 -> ¿Definition of Done? | E13: ='Product Backlog HUs'!$L$29 -> NO
A14: Conversación historia
A15: Requisito de información: | E15: (codigo, nombre, cantidad, unidad_medida, descripcion)
A16: Prototipo: | E16: HU28 - CREAR PRODUCTO.jpg
A17: Catálogo de mensajes: | E17: Catálogo de mensajes.xlsx
A18: Catálogo de parámetros: | E18: Catálogo de parámetros.xlsx
A19: Restricciones de diseño: | E19: <Nombre y enlace al documento de restricciones de diseño que aplican para la HU en especial>
A20: * Deben tenerse en cuenta los campos descritos en el requisito de información que no deben ser visibles por el usuario.
A21: * Al momento de hacer la validación de una asociación previamente registrada con el mismo nombre, se validará contenido, más no temas de mayúsculas y minúsculas.
A22: * Otros aspectos de aclaración de interés para el cumplimiento de la HU.
A23: Conversación aspectos generales y transversales
A24: Aspectos generales: | E24: <Nombre y enlace a documento con listado de aspectos generales que aplican para todas las HU>
A25: Criterios aceptación
A26: Código | B26: Escenario | G26: Estado | I26: Observación
G27: Aceptado | H27: No aceptado
A28: CA1 | B28: Dado que un Cliente desea crear un nuevo producto, cuando complete correctamente todos los campos requeridos y confirme la acción, entonces el sistema guarda la información, muestra un mensaje de éxito (GEN_USU_EXI_00001) y el producto queda disponible para su gestión dentro de la aplicación.
A29: CA2 | B29: Dado que un Cliente intenta crear un nuevo producto, cuando deje uno o más campos obligatorios vacíos, entonces el sistema bloquea el registro y muestra un mensaje de error (GEN_USU_ERR_00002) indicando que debe completar los campos requeridos.

Sheet HU29
A1: <-Volver al listado
A2: Título
A3: ='Product Backlog HUs'!D30 -> HU29-Editar producto
A4: Tarjeta
A5: Como | B5: ='Product Backlog HUs'!$E$30 -> Cliente
A6: Necesito | B6: ='Product Backlog HUs'!$F$30 -> necesito editar la informacion de un producto
A7: Para | B7: ='Product Backlog HUs'!$G$30 -> con el fin de mantener actualizados los productos existentes en la app
A8: ='Product Backlog HUs'!$H$30 -> Como Cliente, necesito editar la informacion de un producto, con el fin de mantener actualizados los productos existentes en la app
A9: Tallaje
A10: ='Product Backlog HUs'!$I$1 -> Talla | E10: ='Product Backlog HUs'!$I$30 -> M
A11: ='Product Backlog HUs'!$J$1 -> Puntos de historia de usuario | E11: ='Product Backlog HUs'!$J$30 -> 3
A12: ='Product Backlog HUs'!$K$1 -> ¿Definition of Ready? | E12: ='Product Backlog HUs'!$K$30 -> NO
A13: ='Product Backlog HUs'!$L$1 -> ¿Definition of Done? | E13: ='Product Backlog HUs'!$L$30 -> NO
A14: Conversación historia
A15: Requisito de información: | E15: (codigo, nombre, cantidad, unidad_medida, descripcion)
A16: Prototipo: | E16: HU29 - EDITAR PRODUCTO.jpg
A17: Catálogo de mensajes: | E17: Catálogo de mensajes.xlsx
A18: Catálogo de parámetros: | E18: Catálogo de parámetros.xlsx
A19: Restricciones de diseño: | E19: <Nombre y enlace al documento de restricciones de diseño que aplican para la HU en especial>
A20: * Deben tenerse en cuenta los campos descritos en el requisito de información que no deben ser visibles por el usuario.
A21: * Al momento de hacer la validación de una asociación previamente registrada con el mismo nombre, se validará contenido, más no temas de mayúsculas y minúsculas.
A22: * Otros aspectos de aclaración de interés para el cumplimiento de la HU.
A23: Conversación aspectos generales y transversales
A24: Aspectos generales: | E24: <Nombre y enlace a documento con listado de aspectos generales que aplican para todas las HU>
A25: Criterios aceptación
A26: Código | B26: Escenario | G26: Estado | I26: Observación
G27: Aceptado | H27: No aceptado
A28: CA1 | B28: Dado que un Cliente quiere editar los datos de un producto, cuando ingrese información válida y guarde los cambios, entonces el sistema actualiza los datos de la sede en la base de datos, registra la modificación en el historial y muestra un mensaje de éxito (GEN_USU_EXI_00001) indicando que la actualización fue realizada correctamente.
A29: CA2 | B29: Dado que un Cliente quiere editar los datos de un producto, cuando ingrese información incompleta o no cumpla con los formatos requeridos (nombre, direccion), entonces el sistema bloquea la acción, muestra un mensaje de error (GEN_USU_ERR_00002) y resalta los campos con errores para que sean corregidos.

Sheet HU30
A1: <-Volver al listado
A2: Título
A3: ='Product Backlog HUs'!D31 -> HU30-Consultar producto
A4: Tarjeta
A5: Como | B5: ='Product Backlog HUs'!$E$31 -> Cliente
A6: Necesito | B6: ='Product Backlog HUs'!$F$31 -> necesito consultar los produtos existentes en la app
A7: Para | B7: ='Product Backlog HUs'!$G$31 -> con el fin de conocer los productos disponibles cuando este creando una solicitud de cotización
A8: ='Product Backlog HUs'!$H$31 -> Como Cliente, necesito consultar los produtos existentes en la app, con el fin de conocer los productos disponibles cuando este creando una solicitud de cotización
A9: Tallaje
A10: ='Product Backlog HUs'!$I$1 -> Talla | E10: ='Product Backlog HUs'!$I$31 -> S
A11: ='Product Backlog HUs'!$J$1 -> Puntos de historia de usuario | E11: ='Product Backlog HUs'!$J$31 -> 2
A12: ='Product Backlog HUs'!$K$1 -> ¿Definition of Ready? | E12: ='Product Backlog HUs'!$K$31 -> NO
A13: ='Product Backlog HUs'!$L$1 -> ¿Definition of Done? | E13: ='Product Backlog HUs'!$L$31 -> NO
A14: Conversación historia
A15: Requisito de información: | E15: (codigo, nombre)
A16: Prototipo: | E16: HU30 - CONSULTAR PRODUCTO.jpg
A17: Catálogo de mensajes: | E17: Catálogo de mensajes.xlsx
A18: Catálogo de parámetros: | E18: Catálogo de parámetros.xlsx
A19: Restricciones de diseño: | E19: <Nombre y enlace al documento de restricciones de diseño que aplican para la HU en especial>
A20: * Deben tenerse en cuenta los campos descritos en el requisito de información que no deben ser visibles por el usuario.
A21: * Al momento de hacer la validación de una asociación previamente registrada con el mismo nombre, se validará contenido, más no temas de mayúsculas y minúsculas.
A22: * Otros aspectos de aclaración de interés para el cumplimiento de la HU.
A23: Conversación aspectos generales y transversales
A24: Aspectos generales: | E24: <Nombre y enlace a documento con listado de aspectos generales que aplican para todas las HU>
A25: Criterios aceptación
A26: Código | B26: Escenario | G26: Estado | I26: Observación
G27: Aceptado | H27: No aceptado
A28: CA1 | B28: Dado que un Cliente ingresa a la sección de crear una solicitud de cotización o listar los productos, cuando selecciona la opción para elegir un producto, entonces el sistema debe mostrar una lista completa de los productos existentes.
A29: CA2 | B29: Dado que un Cliente ha consultado la lista de productos, cuando selecciona un producto de la lista, entonces el sistema debe permitir que este sea registrado como parte de la información de la solicitud de cotizacion.
A30: CA3 | B30: Dado que un Cliente necesita encontrar un producto en específico en la lista, cuando ingresa el nombre o parte del nombre del producto en un campo de búsqueda, entonces el sistema debe filtrar y mostrar solo los productos que coincidan con el criterio de búsqueda.

Sheet HU31
A1: <-Volver al listado
A2: Título
A3: ='Product Backlog HUs'!D32 -> HU31-Eliminar producto
A4: Tarjeta
A5: Como | B5: ='Product Backlog HUs'!$E$32 -> Cliente
A6: Necesito | B6: ='Product Backlog HUs'!$F$32 -> necesito eliminar un producto existente
A7: Para | B7: ='Product Backlog HUs'!$G$32 -> con el fin de descartar los productos innecesarios permitiendo asi una correcta depuración y optimización de la base de datos de la app
A8: ='Product Backlog HUs'!$H$32 -> Como Cliente, necesito eliminar un producto existente, con el fin de descartar los productos innecesarios permitiendo asi una correcta depuración y optimización de la base de datos de la app
A9: Tallaje
A10: ='Product Backlog HUs'!$I$1 -> Talla | E10: ='Product Backlog HUs'!$I$32 -> S
A11: ='Product Backlog HUs'!$J$1 -> Puntos de historia de usuario | E11: ='Product Backlog HUs'!$J$32 -> 2
A12: ='Product Backlog HUs'!$K$1 -> ¿Definition of Ready? | E12: ='Product Backlog HUs'!$K$32 -> NO
A13: ='Product Backlog HUs'!$L$1 -> ¿Definition of Done? | E13: ='Product Backlog HUs'!$L$32 -> NO
A14: Conversación historia
A15: Requisito de información: | E15: (codigo, nombre)
A16: Prototipo: | E16: HU31 - ELIMINAR PRODUCTO.jpg
A17: Catálogo de mensajes: | E17: Catálogo de mensajes.xlsx
A18: Catálogo de parámetros: | E18: Catálogo de parámetros.xlsx
A19: Restricciones de diseño: | E19: <Nombre y enlace al documento de restricciones de diseño que aplican para la HU en especial>
A20: * Deben tenerse en cuenta los campos descritos en el requisito de información que no deben ser visibles por el usuario.
A21: * Al momento de hacer la validación de una asociación previamente registrada con el mismo nombre, se validará contenido, más no temas de mayúsculas y minúsculas.
A22: * Otros aspectos de aclaración de interés para el cumplimiento de la HU.
A23: Conversación aspectos generales y transversales
A24: Aspectos generales: | E24: <Nombre y enlace a documento con listado de aspectos generales que aplican para todas las HU>
A25: Criterios aceptación
A26: Código | B26: Escenario | G26: Estado | I26: Observación
G27: Aceptado | H27: No aceptado
A28: CA1 | B28: Dado que un Cliente desea eliminar un producto registrado, cuando confirme la acción y no existan restricciones que impidan la eliminación, entonces el sistema elimina el producto de la base de datos, registra la acción en el historial y muestra un mensaje de éxito (GEN_USU_EXI_00001) indicando que el producto ha sido eliminado correctamente.
