Workbook

Sheet Modelo dominio anémico contexto

Sheet Listado Objetos de Dominio
A1: Subdominio/Contexto: | B1: Cliente
A2: Nombre | B2: Descripción | C2: Tipo | D2: Contexto
A3: Departamento | B3: Indica el departamento al que pertenece la ciudad donde reside el cliente | C3: Propio | D3: Usuario
A4: Ciudad | B4: Se refiere a la ciudad donde reside el cliente y/o donde está ubicado su negocio | C4: Propio | D4: Usuario
A5: Usuario | B5: Describe al usuario que realiza las solicitudes de cotización en la aplicación | C5: Propio | D5: Usuario
A6: Negocio | B6: Se refiere al negocio que ha registrado el cliente en la aplicación | C6: Propio | D6: Usuario
A7: Sede | B7: Se refiere a la o las sedes/sucursales que posee el negocio del cliente | C7: Propio | D7: Usuario
A8: Colaborador | B8: Indica a un usuario externo encargado de ayudar al cliente con las solicitudes de cotización | C8: Propio | D8: Usuario
A9: Solicitud cotización | B9: Se refiere al documento que diligencia el cliente solicitando la cotización de ciertos productos a los proveedores | C9: Propio | D9: Usuario
A10: Producto | B10: Indica el producto que se crea en la solicitud de cotización | C10: Propio | D10: Usuario
A11: Cotización | B11: Se refiere a la respuesta que da el proveedor a la solicitud de cotización del cliente | C11: Referenciado | D11: Proveedor
A12: Notificación | B12: Se refiere a las alertas y notificaciones que recibe el usuario | C12: Propio | D12: Usuario
A13: Plan de suscripción | B13: Indica el plan al que el usuario se encuentra inscrito y los beneficios que posee con este | C13: Propio | D13: Usuario
A14: Transacción de pago | B14: Indica la transaccion de pago del usuario para adquirir un plan de suscripción | C14: Propio | D14: Usuario

Sheet Valores
A1: Tipo Objeto Dominio
A2: Tipo | B2: Descripción
A3: Propio | B3: Cuando el objeto de dominio es parte del contexto actual
A4: Referenciado | B4: Cuando el objeto de dominio es parte de otro contexto

Sheet Departamento
A1: <-Volver al inicio
A2: Objeto de Dominio: | B2: ='Listado Objetos de Dominio'!$A$3 -> Departamento
A3: Descripción: | B3: ='Listado Objetos de Dominio'!$B$3 -> Indica el departamento al que pertenece la ciudad donde reside el cliente
A4: Atributo | B4: Tipo de Dato | C4: Longitud mínima | D4: Longitud máxima | E4: Precisión | F4: Rango Inicial | G4: Rango Final | H4: Formato | I4: Valor por defecto | J4: Regla especial | K4: ¿Auto generado? | L4: ¿Calculado? | M4: ¿Obligatorio? | N4: ¿Sensible? | O4: ¿Identifica al registro? | P4: Descripción | Q4: =A16 -> Consultar | R4: =A17 -> 0 | S4: =A18 -> 0 | T4: =A19 -> 0
A5: Codigo | B5: Entero | F5: Mayor que 0 | K5: Si | L5: No | M5: Si | N5: No | O5: Si | P5: Atributo que representa el código que identifica a un departamento determinado y asegura que sea único.
A6: Nombre | B6: Texto | C6: 1 | D6: 50 | H6: Solo letras y espacios | K6: No | L6: No | M6: Si | P6: Atributo que representa el nombre que se le asigna a un departamento determinado.
A10: Combinaciones únicas
A11: Nombre combinación | B11: Descripción | C11: Atributos
A14: Responsabilidad | C14: Descripción | G14: Entradas | J14: Salida | O14: Políticas (Reglas de Negocio) | Q14: Excepción
G15: Parámetro | H15: Tipo de dato | I15: Descripción | J15: Tipo de Dato | K15: Descripción | O15: Política | P15: Descripción | Q15: Detalle | R15: ¿Qué hago?
A16: Consultar | C16: Servicio de negocio que permite consultar la información de los departamentos. | I16: Una entidad de tipo Departamento, que contendrá los filtros de consulta permitidos de acuerdo al requisito de información. | K16: Un listado con la información de todos los departamentos que cumplen con los parámetros de filtrado recibidos. | O16: N/A | Q16: N/A

Sheet Usuario
A1: <-Volver al inicio
A2: Objeto de Dominio: | B2: ='Listado Objetos de Dominio'!$A$5 -> Usuario
A3: Descripción: | B3: ='Listado Objetos de Dominio'!$B$5 -> Describe al usuario que realiza las solicitudes de cotización en la aplicación
A4: Atributo | B4: Tipo de Dato | C4: Longitud mínima | D4: Longitud máxima | E4: Precisión | F4: Rango Inicial | G4: Rango Final | H4: Formato | I4: Valor por defecto | J4: Regla especial | K4: ¿Auto generado? | L4: ¿Calculado? | M4: ¿Obligatorio? | N4: ¿Sensible? | O4: ¿Identifica al registro? | P4: Descripción | Q4: =A21 -> loginUser | R4: =A22 -> registerUser | S4: =A23 -> getUser | T4: =A24 -> updateUser
A5: id | B5: uuid | C5: 36 | D5: 36 | E5: - | F5: - | G5: - | H5: UUID | I5: - | J5: Auto generado por la base de datos | K5: Si | L5: No | M5: Si | N5: No | O5: Si | P5: Identificador único del usuario
A6: identificacion | B6: alfanumerico | C6: 5 | D6: 20 | E6: - | F6: - | G6: - | H6: Numeros y letras | I6: - | J6: Debe ser único por usuario | K6: No | L6: No | M6: Si | N6: No | O6: No | P6: DNI o NIT del usuario
A7: nombre | B7: alfanumerico | C7: 1 | D7: 100 | E7: - | F7: - | G7: - | H7: Texto | I7: - | J7: - | K7: No | L7: No | M7: Si | N7: No | O7: No | P7: Nombre del usuario
A8: apellido | B8: alfanumerico | C8: 1 | D8: 100 | E8: - | F8: - | G8: - | H8: Texto | I8: - | J8: - | K8: No | L8: No | M8: Si | N8: No | O8: No | P8: Apellido del usuario
A9: correo | B9: alfanumerico | C9: 5 | D9: 150 | E9: - | F9: - | G9: - | H9: Email | I9: - | J9: Formato email válido y único | K9: No | L9: No | M9: Si | N9: No | O9: No | P9: Correo electrónico
A10: contraseña | B10: password | C10: 8 | D10: 100 | E10: - | F10: - | G10: - | H10: Hashed | I10: - | J10: Se almacena encriptado con Bcrypt | K10: No | L10: No | M10: Si | N10: Si | O10: No | P10: Contraseña de acceso
A11: departamento | B11: departamento | C11: - | D11: - | E11: - | F11: - | G11: - | H11: Texto | I11: - | J11: Referencia a lista de departamentos | K11: No | L11: No | M11: Si | N11: No | O11: No | P11: Departamento de ubicación
A12: ciudad | B12: ciudad | C12: - | D12: - | E12: - | F12: - | G12: - | H12: Texto | I12: - | J12: Referencia a lista de ciudades | K12: No | L12: No | M12: Si | N12: No | O12: No | P12: Ciudad de ubicación
A13: rol | B13: enum | C13: - | D13: - | E13: - | F13: - | G13: - | H13: OWNER|COLLABORATOR | I13: OWNER | J13: Control de acceso basado en roles | K13: No | L13: No | M13: Si | N13: No | O13: No | P13: Rol del usuario en el sistema
A14: Idpropietario | B14: uuid | C14: - | D14: - | E14: - | F14: - | G14: - | H14: UUID | I14: - | J14: Asignado si es un colaborador | K14: No | L14: No | M14: No | N14: No | O14: No | P14: ID del dueño de la cuenta
A15: Idplan | B15: uuid | D15: - | E15: - | F15: - | G15: - | H15: UUID | I15: - | J15: Relación con el plan de suscripción | K15: No | L15: No | M15: No | N15: No | O15: No | P15: Plan actual
A16: FechaInicioPlan | B16: date | C16: - | D16: - | E16: - | F16: - | G16: - | H16: Date | I16: - | J16: Fecha de inicio del plan actual | K16: No | L16: No | M16: No | N16: No | O16: No | P16: Fecha de activación del plan
A19: Responsabilidad | C19: Descripción | G19: Entradas | J19: Salida | O19: Políticas (Reglas de Negocio) | Q19: Excepción
G20: Parámetro | H20: Tipo de dato | I20: Descripción | J20: Tipo de Dato | K20: Descripción | O20: Política | P20: Descripción | Q20: Detalle | R20: ¿Qué hago?
A21: loginUser | C21: Servicio que permite al usuario autenticarse y generar un token JWT | G21: Email, Password | J21: JSON | K21: Token, Datos Usuario | O21: Credenciales válidas | Q21: Credenciales inválidas
A22: registerUser | C22: Servicio que permite la creación de una nueva cuenta de usuario | G22: Datos Usuario | J22: JSON | K22: Usuario creado | O22: Email único | Q22: Email ya registrado
A23: getUser | C23: Servicio que obtiene el perfil del usuario autenticado | G23: ID Usuario | J23: JSON | K23: Detalle Usuario | O23: Token válido | Q23: No autorizado
A24: updateUser | C24: Servicio que permite modificar los datos del perfil | G24: Datos a editar | H24: 'Tipo Relación Institución'!A6 | J24: JSON | K24: Usuario actualizado | O24: Permisos de edición | Q24: Datos inválidos
A25: deleteUser | C25: Servicio que permite eliminar la cuenta y datos asociados | G25: ID Usuario | J25: JSON | K25: Confirmación | O25: Confirmación del usuario | Q25: Error de proceso

Sheet Ciudad
A1: <-Volver al inicio
A2: Objeto de Dominio: | B2: ='Listado Objetos de Dominio'!$A$4 -> Ciudad
A3: Descripción: | B3: ='Listado Objetos de Dominio'!$B$4 -> Se refiere a la ciudad donde reside el cliente y/o donde está ubicado su negocio
A4: Atributo | B4: Tipo de Dato | C4: Longitud mínima | D4: Longitud máxima | E4: Precisión | F4: Rango Inicial | G4: Rango Final | H4: Formato | I4: Valor por defecto | J4: Regla especial | K4: ¿Auto generado? | L4: ¿Calculado? | M4: ¿Obligatorio? | N4: ¿Sensible? | O4: ¿Identifica al registro? | P4: Descripción | Q4: =A16 -> Consultar | R4: =#REF! -> #REF! | S4: =#REF! -> #REF! | T4: =#REF! -> #REF!
A5: Codigo | B5: Número entero | F5: Mayo que 0 | K5: Si | L5: No | M5: Si | N5: No | O5: Si
A6: Nombre | B6: Texto | C6: 1 | D6: 50 | H6: Solo letras y espacios | K6: No | L6: No | M6: Si | N6: No
A7: Departamento | B7: Departamento | J7: Aplican las reglas definidas en el requisito de información propio de Departamento | M7: Si
A10: Combinaciones únicas
A11: Nombre combinación | B11: Descripción | C11: Atributos
A14: Responsabilidad | C14: Descripción | G14: Entradas | J14: Salida | O14: Políticas (Reglas de Negocio) | Q14: Excepción
G15: Parámetro | H15: Tipo de dato | I15: Descripción | J15: Tipo de Dato | K15: Descripción | O15: Política | P15: Descripción | Q15: Detalle | R15: ¿Qué hago?
A16: Consultar | C16: Servicio de negocio que permite consultar la información de las ciudades. | I16: Una entidad de tipo Ciudad, que contendrá los filtros de consulta permitidos de acuerdo al requisito de información. | K16: Un listado con la información de todas las ciudades que cumplen con los parámetros de filtrado recibidos.

Sheet Negocio
A1: <-Volver al inicio
A2: Objeto de Dominio: | B2: ='Listado Objetos de Dominio'!$A$6 -> Negocio
A3: Descripción: | B3: ='Listado Objetos de Dominio'!$B$6 -> Se refiere al negocio que ha registrado el cliente en la aplicación
A4: Atributo | B4: Tipo de Dato | C4: Longitud mínima | D4: Longitud máxima | E4: Precisión | F4: Rango Inicial | G4: Rango Final | H4: Formato | I4: Valor por defecto | J4: Regla especial | K4: ¿Auto generado? | L4: ¿Calculado? | M4: ¿Obligatorio? | N4: ¿Sensible? | O4: ¿Identifica al registro? | P4: Descripción | Q4: =A20 -> registerBusiness | R4: =A21 -> getBusiness | S4: =A22 -> updateBusiness | T4: =A23 -> verifyBusiness
A5: id | B5: uuid | C5: 36 | D5: 36 | E5: - | F5: - | G5: - | H5: UUID | I5: - | J5: Auto generado | K5: Si | L5: No | M5: Si | N5: No | O5: Si | P5: ID único del negocio
A6: nit | B6: alfanumerico | C6: 5 | D6: 20 | E6: - | F6: - | G6: - | H6: NIT | I6: - | J6: Debe ser único | K6: No | L6: No | M6: Si | N6: No | O6: No | P6: NIT de la empresa
A7: nombre | B7: alfanumerico | C7: 1 | D7: 150 | E7: - | F7: - | G7: - | H7: Texto | I7: - | J7: - | K7: No | L7: No | M7: Si | N7: No | O7: No | P7: Nombre de la empresa
A8: descripcion | B8: alfanumerico | C8: 1 | D8: 500 | E8: - | F8: - | G8: - | H8: Texto | I8: - | J8: - | K8: No | L8: No | M8: Si | N8: No | O8: No | P8: Descripción del negocio
A9: direccion | B9: alfanumerico | C9: 1 | D9: 200 | E9: - | F9: - | G9: - | H9: Dirección | I9: - | J9: - | K9: No | L9: No | M9: Si | N9: No | O9: No | P9: Dirección principal
A10: usuario | B10: usuario | C10: - | D10: - | E10: - | F10: - | G10: - | H10: UUID | I10: - | J10: Dueño del negocio | K10: No | L10: No | M10: Si | N10: No | O10: No | P10: ID del usuario propietario
A11: estado | B11: enum | C11: - | D11: - | E11: - | F11: - | G11: - | H11: PENDING|ACTIVE|REJECTED | I11: PENDING | J11: Estado de verificación por admin | K11: No | L11: No | M11: Si | N11: No | O11: No | P11: Estado del negocio
A12: rut | B12: alfanumerico | C12: - | D12: - | E12: - | F12: - | G12: - | H12: URL | I12: - | J12: Ruta al archivo PDF del RUT | K12: No | L12: No | M12: No | N12: No | O12: No | P12: URL del RUT cargado
A13: camara de comercio | B13: alfanumerico | C13: - | D13: - | E13: - | F13: - | G13: - | H13: URL | I13: - | J13: Ruta al PDF de Cámara de Comercio | K13: No | L13: No | M13: No | N13: No | O13: No | P13: URL de Cámara de Comercio
A18: Responsabilidad | C18: Descripción | G18: Entradas | J18: Salida | O18: Políticas (Reglas de Negocio) | Q18: Excepción
G19: Parámetro | H19: Tipo de dato | I19: Descripción | J19: Tipo de Dato | K19: Descripción | O19: Política | P19: Descripción | Q19: Detalle | R19: ¿Qué hago?
A20: registerBusiness | C20: Registra un nuevo negocio y carga sus documentos legales | G20: Datos negocio + Files | J20: JSON | K20: Negocio pendiente | O20: Usuario autenticado | Q20: Archivos inválidos
A21: getBusiness | C21: Obtiene la información comercial de un negocio específico | G21: ID Negocio | J21: JSON | K21: Detalle negocio | O21: Público | Q21: No encontrado
A22: updateBusiness | C22: Permite editar la información del negocio | G22: Datos negocio | J22: JSON | K22: Negocio actualizado | O22: Es el propietario | Q22: No autorizado
A23: verifyBusiness | C23: Proceso administrativo para validar el estado del negocio | G23: Estado nuevo | J23: JSON | K23: Estado actualizado | O23: Es administrador | Q23: Sin permisos
A24: deleteBusiness | C24: Elimina el registro de la empresa del sistema | G24: ID Negocio | J24: JSON | K24: Confirmación | O24: Sin solicitudes activas | Q24: Tiene dependencias

Sheet Sede
A1: <-Volver al inicio
A2: Objeto de Dominio: | B2: ='Listado Objetos de Dominio'!$A$7 -> Sede
A3: Descripción: | B3: ='Listado Objetos de Dominio'!$B$7 -> Se refiere a la o las sedes/sucursales que posee el negocio del cliente
A4: Atributo | B4: Tipo de Dato | C4: Longitud mínima | D4: Longitud máxima | E4: Precisión | F4: Rango Inicial | G4: Rango Final | H4: Formato | I4: Valor por defecto | J4: Regla especial | K4: ¿Auto generado? | L4: ¿Calculado? | M4: ¿Obligatorio? | N4: ¿Sensible? | O4: ¿Identifica al registro? | P4: Descripción | Q4: =A17 -> 'Objeto Dominio N'!R4 | R4: =A18 -> Actualizar datos | S4: =A19 -> consultar | T4: =A20 -> eliminar
A5: id | B5: uuid | C5: 36 | D5: 36 | E5: - | F5: - | G5: - | H5: UUID | I5: - | K5: Si | L5: No | M5: Si | N5: No | O5: Si | P5: ID único de la sede
A6: name | B6: alfanumerico | C6: 1 | D6: 100 | E6: - | F6: - | G6: - | H6: Texto | I6: - | K6: No | L6: No | M6: Si | N6: No | O6: No | P6: Nombre de la sede
A7: direccion | B7: alfanumerico | C7: 1 | D7: 200 | E7: - | F7: - | G7: - | H7: Dirección | I7: - | K7: No | L7: No | M7: Si | N7: No | O7: No | P7: Ubicación física
A8: ciudad | B8: ciudad | C8: - | D8: - | E8: - | F8: - | G8: - | H8: UUID | I8: - | J8: Aplica las reglas definidas en el dominio de ciudad | K8: No | L8: No | M8: Si | N8: No | O8: No | P8: Ciudad de la sede
A9: negocio | B9: negocio | C9: - | D9: - | E9: - | F9: - | G9: - | H9: UUID | I9: - | J9: Aplica las reglas definidas en el dominio de negocio | K9: No | L9: No | M9: Si | N9: No | O9: No | P9: ID del negocio padre
Q15: Excepción
Q16: Detalle | R16: ¿Qué hago?
A17: 'Objeto Dominio N'!R4
A18: Actualizar datos | C18: Servicio que permite actualizar la informacion de una sede existente
A19: consultar | C19: Servicio que permite consultar las sede existentes en la aplicacion
A20: eliminar | C20: Servicio que permite eliminar una sede existente

Sheet Colaborador
A1: <-Volver al inicio
A2: Objeto de Dominio: | B2: ='Listado Objetos de Dominio'!$A$8 -> Colaborador
A3: Descripción: | B3: ='Listado Objetos de Dominio'!$B$8 -> Indica a un usuario externo encargado de ayudar al cliente con las solicitudes de cotización
A4: Atributo | B4: Tipo de Dato | C4: Longitud mínima | D4: Longitud máxima | E4: Precisión | F4: Rango Inicial | G4: Rango Final | H4: Formato | I4: Valor por defecto | J4: Regla especial | K4: ¿Auto generado? | L4: ¿Calculado? | M4: ¿Obligatorio? | N4: ¿Sensible? | O4: ¿Identifica al registro? | P4: Descripción | Q4: =A17 -> invitar | R4: =#REF! -> #REF! | S4: =#REF! -> #REF! | T4: =#REF! -> #REF!
A5: id | B5: uuid | C5: 36 | D5: 36 | E5: - | F5: - | G5: - | H5: UUID | I5: - | K5: Si | L5: No | M5: Si | N5: No | O5: Si | P5: ID único del colaborador
A6: correo | B6: alfanumerico | C6: 5 | D6: 150 | E6: - | F6: - | G6: - | H6: Email | I6: - | K6: No | L6: No | M6: Si | N6: No | O6: No | P6: Correo electrónico
A7: estado_invitacion | B7: enum | C7: - | D7: - | E7: - | F7: - | G7: - | H7: PENDING|ACCEPTED|REJECTED | I7: PENDING | K7: No | L7: No | M7: Si | N7: No | O7: No | P7: Estado
A8: fecha_creacion | B8: date | C8: - | D8: - | E8: - | F8: - | G8: - | H8: Date | I8: Now | K8: Si | L8: No | M8: Si | N8: No | O8: No | P8: Fecha de envío
A9: usuario | B9: usuario | C9: - | D9: - | E9: - | F9: - | G9: - | H9: UUID | I9: - | J9: Aplica las reglas definidas en el dominio de usuario | K9: No | L9: No | M9: Si | N9: No | O9: No | P9: Propietario
A15: Responsabilidad | C15: Descripción | G15: Entradas | J15: Salida | O15: Políticas (Reglas de Negocio) | Q15: Excepción
G16: Parámetro | H16: Tipo de dato | I16: Descripción | J16: Tipo de Dato | K16: Descripción | O16: Política | P16: Descripción | Q16: Detalle | R16: ¿Qué hago?
A17: invitar | C17: Envía una invitación por correo a un nuevo colaborador | G17: Email | J17: JSON | K17: Colaborador pendiente | O17: Plan permite más cupos | Q17: Email ya invitado
A18: consultar | C18: Lista colaboradores con invitación aceptada | G18: ID Usuario | J18: JSON | K18: Lista activos | O18: Autenticado | Q18: Sin datos
A19: eliminar colaborador | C19: Elimina a un colaborador del equipo | G19: ID Colaborador | J19: JSON | K19: Confirmación | O19: Es el dueño | Q19: Error
A20: aceptar invitacion | C20: Proceso de aceptación vía link de correo | G20: Token/ID | J20: JSON | K20: Estado ACCEPTED | O20: Invitación existe | Q20: Link expirado
A21: rechazar invitacion | C21: Rechazo de la invitación | G21: Token/ID | J21: JSON | K21: Estado REJECTED | O21: Invitación existe | Q21: Link expirado

Sheet Solicitud Cotizacion
A1: <-Volver al inicio
A2: Objeto de Dominio: | B2: ='Listado Objetos de Dominio'!$A$9 -> Solicitud cotización
A3: Descripción: | B3: ='Listado Objetos de Dominio'!$B$9 -> Se refiere al documento que diligencia el cliente solicitando la cotización de ciertos productos a los proveedores
A4: Atributo | B4: Tipo de Dato | C4: Longitud mínima | D4: Longitud máxima | E4: Precisión | F4: Rango Inicial | G4: Rango Final | H4: Formato | I4: Valor por defecto | J4: Regla especial | K4: ¿Auto generado? | L4: ¿Calculado? | M4: ¿Obligatorio? | N4: ¿Sensible? | O4: ¿Identifica al registro? | P4: Descripción | Q4: =A21 -> registerQuotationRequest | R4: =A22 -> getQuotationRequest | S4: =A23 -> getAllQuotationRequestsByUserId | T4: =A24 -> searchQuotationRequestsByTitle
A5: id | B5: uuid | C5: 36 | D5: 36 | E5: - | F5: - | G5: - | H5: UUID | I5: - | K5: Si | L5: No | M5: Si | N5: No | O5: Si | P5: ID único de la solicitud
A6: titulo | B6: alfanumerico | C6: 5 | D6: 200 | E6: - | F6: - | G6: - | H6: Texto | I6: - | J6: Título breve del requerimiento | K6: No | L6: No | M6: Si | N6: No | O6: No | P6: Título resumido
A7: descripcion | B7: alfanumerico | C7: 1 | D7: 1000 | E7: - | F7: - | G7: - | H7: Texto | I7: - | J7: Detalles adicionales del pedido | K7: No | L7: No | M7: Si | N7: No | O7: No | P7: Descripción detallada
A8: fecha creacion | B8: fecha | C8: - | D8: - | E8: - | F8: - | G8: - | H8: Date | I8: Now | K8: Si | L8: No | M8: Si | N8: No | O8: No | P8: Fecha de creación
A9: fecha expiracion | B9: fecha | C9: - | D9: - | E9: - | F9: - | G9: - | H9: Date | I9: - | J9: Fecha límite para recibir ofertas | K9: No | L9: No | M9: Si | N9: No | O9: No | P9: Fecha límite
A10: estado | B10: enum | C10: - | D10: - | E10: - | F10: - | G10: - | H10: PENDING|OPEN|CLOSED | I10: PENDING | J10: Ciclo de vida de la solicitud | K10: No | L10: No | M10: Si | N10: No | O10: No | P10: Estado actual
A11: sede | B11: sede | C11: - | D11: - | E11: - | F11: - | G11: - | H11: UUID | I11: - | J11: Sede que originó el pedido | K11: No | L11: No | M11: Si | N11: No | O11: No | P11: Sede asociada
A12: usuario | B12: usuario | C12: - | D12: - | E12: - | F12: - | G12: - | H12: UUID | I12: - | J12: Usuario que solicita | K12: No | L12: No | M12: Si | N12: No | O12: No | P12: ID solicitante
A19: Responsabilidad | C19: Descripción | G19: Entradas | J19: Salida | O19: Políticas (Reglas de Negocio) | Q19: Excepción
G20: Parámetro | H20: Tipo de dato | I20: Descripción | J20: Tipo de Dato | K20: Descripción | O20: Política | P20: Descripción | Q20: Detalle | R20: ¿Qué hago?
A21: registerQuotationRequest | C21: Publica una nueva solicitud de cotización al marketplace | G21: Título, Desc, Productos | J21: JSON | K21: Solicitud creada | O21: Créditos/Plan disponible | Q21: Campos incompletos
A22: getQuotationRequest | C22: Consulta el detalle técnico de una solicitud y sus productos | G22: ID Solicitud | J22: JSON | K22: Objeto completo | O22: Acceso público/privado | Q22: No encontrada
A23: getAllQuotationRequestsByUserId | C23: Historial de solicitudes realizadas por el usuario | G23: ID Usuario | J23: JSON | K23: Lista solicitudes | O23: Sesión activa | Q23: Sin datos
A24: searchQuotationRequestsByTitle | C24: Búsqueda dinámica en el marketplace | G24: Keyword | J24: JSON | K24: Resultados filtrados | O24: Texto de búsqueda | Q24: Sin coincidencias
A25: updateQuotationRequest | C25: Permite corregir errores en la solicitud abierta | G25: Nuevos parámetros | J25: JSON | K25: Actualizado | O25: Estado PENDING/OPEN | Q25: Estado CLOSED
A26: closeQuotationRequest | C26: Cierra la recepción de nuevas cotizaciones | G26: ID Solicitud | J26: JSON | K26: Estado CLOSED | O26: Es el autor | Q26: Ya cerrada
A27: deleteQuotationRequest | C27: Elimina permanentemente la solicitud | G27: ID Solicitud | J27: JSON | K27: Confirmación | O27: Sin cotizaciones recibidas | Q27: Error

Sheet Producto
A1: <-Volver al inicio
A2: Objeto de Dominio: | B2: ='Listado Objetos de Dominio'!$A$10 -> Producto
A3: Descripción: | B3: ='Listado Objetos de Dominio'!$B$10 -> Indica el producto que se crea en la solicitud de cotización
A4: Atributo | B4: Tipo de Dato | C4: Longitud mínima | D4: Longitud máxima | E4: Precisión | F4: Rango Inicial | G4: Rango Final | H4: Formato | I4: Valor por defecto | J4: Regla especial | K4: ¿Auto generado? | L4: ¿Calculado? | M4: ¿Obligatorio? | N4: ¿Sensible? | O4: ¿Identifica al registro? | P4: Descripción | Q4: =A18 -> 0 | R4: =A19 -> 0 | S4: =A20 -> 0 | T4: =A21 -> 0
A5: id | B5: uuid | C5: 36 | D5: 36 | E5: - | F5: - | G5: - | H5: UUID | I5: - | K5: Si | L5: No | M5: Si | N5: No | O5: Si | P5: ID del ítem
A6: nombre | B6: alfanumerico | C6: 1 | D6: 150 | E6: - | F6: - | G6: - | H6: Texto | I6: - | K6: No | L6: No | M6: Si | N6: No | O6: No | P6: Nombre del producto
A7: cantidad | B7: numero | C7: - | D7: - | E7: - | F7: 1 | G7: - | H7: Integer | I7: - | K7: No | L7: No | M7: Si | N7: No | O7: No | P7: Cantidad requerida
A8: unidad medida | B8: alfanumerico | C8: - | D8: - | E8: - | F8: Texto | G8: - | H8: - | I8: - | J8: Unidad (Kg, Un, Mts, etc) | K8: No | L8: No | M8: Si | N8: No | O8: No | P8: Unidad de medida
A9: descripcion | B9: alfanumerico | C9: 0 | D9: 500 | E9: - | F9: - | G9: - | H9: Texto | I9: - | K9: No | L9: No | M9: No | N9: No | O9: No | P9: Notas del producto
A10: solicitud cotizacion | B10: solicitud cotizacion | C10: - | D10: - | E10: - | F10: - | G10: - | H10: UUID | I10: - | J10: ID de la solicitud padre | K10: No | L10: No | M10: Si | N10: No | O10: No | P10: Clave foránea solicitud
A11: fecha creacion | B11: date | C11: - | D11: - | E11: - | F11: - | G11: - | H11: Date | I11: Now | K11: Si | L11: No | M11: Si | N11: No | O11: No | P11: Fecha registro item
Q16: Excepción
Q17: Detalle | R17: ¿Qué hago?

Sheet Cotizacion
A1: <-Volver al inicio
A2: Objeto de Dominio: | B2: ='Listado Objetos de Dominio'!$A$11 -> Cotización
A3: Descripción: | B3: ='Listado Objetos de Dominio'!$B$11 -> Se refiere a la respuesta que da el proveedor a la solicitud de cotización del cliente
A4: Atributo | B4: Tipo de Dato | C4: Longitud mínima | D4: Longitud máxima | E4: Precisión | F4: Rango Inicial | G4: Rango Final | H4: Formato | I4: Valor por defecto | J4: Regla especial | K4: ¿Auto generado? | L4: ¿Calculado? | M4: ¿Obligatorio? | N4: ¿Sensible? | O4: ¿Identifica al registro? | P4: Descripción | Q4: =A21 -> crear cotizacion | R4: =A22 -> consultar | S4: =#REF! -> #REF! | T4: =#REF! -> #REF!
A5: id | B5: uuid | C5: 36 | D5: 36 | E5: - | F5: - | G5: - | H5: UUID | I5: - | K5: Si | L5: No | M5: Si | N5: No | O5: Si | P5: ID de la oferta
A6: fecha respuesta | B6: fecha | C6: - | D6: - | E6: - | F6: - | G6: - | H6: Date | I6: Now | J6: Fecha de emisión | K6: Si | L6: No | M6: Si | N6: No | O6: No | P6: Fecha creación
A7: fecha limite | B7: fecha | C7: - | D7: - | E7: - | F7: - | G7: - | H7: Date | I7: - | J7: Validez de la oferta | K7: No | L7: No | M7: Si | N7: No | O7: No | P7: Vigencia
A8: valor | B8: numero | C8: - | D8: - | E8: 2 | F8: 0 | G8: - | H8: Monetario | I8: - | J8: Valor total de la oferta | K8: No | L8: No | M8: Si | N8: No | O8: No | P8: Precio total
A9: tiempo entrega | B9: fecha/texto | C9: - | D9: - | E9: - | F9: - | G9: - | H9: Date | I9: - | J9: Fecha estimada de entrega | K9: No | L9: No | M9: Si | N9: No | O9: No | P9: Plazo entrega
A10: descripcion | B10: alfanumerico | C10: 1 | D10: 1000 | E10: - | F10: - | G10: - | H10: Texto | I10: - | J10: Términos y condiciones | K10: No | L10: No | M10: Si | N10: No | O10: No | P10: Observaciones
A11: estado | B11: enum | C11: - | D11: - | E11: - | F11: - | G11: - | H11: DRAFT|PENDING|ACCEPTED|EXPIRED | I11: DRAFT | J11: Estado gestión oferta | K11: No | L11: No | M11: Si | N11: No | O11: No | P11: Estado
A12: valor unitario | B12: json | C12: - | D12: - | E12: - | F12: - | G12: - | H12: Array | I12: - | J12: Desglose de valores por producto | K12: No | L12: Si | M12: No | N12: No | O12: No | P12: Valores unitarios
A13: solicitud cotizacion | B13: solicitud cotizacion | C13: - | D13: - | E13: - | F13: - | G13: - | H13: UUID | I13: - | J13: Aplica las reglas definidas en el dominio de solicitud cotizacion | K13: No | L13: No | M13: Si | N13: No | O13: No | P13: Solicitud vinculada
A14: usuario | B14: usuario | C14: - | D14: - | E14: - | F14: - | G14: - | H14: UUID | I14: - | J14: Aplica las reglas definidas en el dominio de usuario | K14: No | L14: No | M14: Si | N14: No | O14: No | P14: ID del usuario al que pertenece la solicitud
A19: Responsabilidad | C19: Descripción | G19: Entradas | J19: Salida | O19: Políticas (Reglas de Negocio) | Q19: Excepción
G20: Parámetro | H20: Tipo de dato | I20: Descripción | J20: Tipo de Dato | K20: Descripción | O20: Política | P20: Descripción | Q20: Detalle | R20: ¿Qué hago?
A21: crear cotizacion | C21: Envía una oferta formal a una solicitud del marketplace | G21: Datos cotización | J21: JSON | K21: Oferta enviada | O21: No es su propia solicitud | Q21: Solicitud cerrada
A22: consultar | C22: Ver detalle de una oferta recibida o enviada | G22: ID Cotización | J22: JSON | K22: Objeto cotización | O22: Dueño o Solicitante | Q22: No autorizado
A23: editar cotizacion | C23: Permite al proveedor ajustar su oferta | G23: Nuevos valores | J23: JSON | K23: Actualizada | O23: Estado DRAFT o PENDING | Q23: Ya aceptada
A24: comparar cotizaciones | C24: Algoritmo de selección de mejor oferta | G24: ID Solicitud | J24: JSON | K24: Ranking | O24: Tener mínimo 2 ofertas | Q24: Pocas ofertas
A25: eliminar cotizacion | C25: Retira la oferta del proceso | G25: ID Cotización | J25: JSON | K25: Eliminada | O25: No aceptada aún | Q25: Error

Sheet Notificación
A1: <-Volver al inicio
A2: Objeto de Dominio: | B2: ='Listado Objetos de Dominio'!$A$12 -> Notificación
A3: Descripción: | B3: ='Listado Objetos de Dominio'!$B$12 -> Se refiere a las alertas y notificaciones que recibe el usuario
A4: Atributo | B4: Tipo de Dato | C4: Longitud mínima | D4: Longitud máxima | E4: Precisión | F4: Rango Inicial | G4: Rango Final | H4: Formato | I4: Valor por defecto | J4: Regla especial | K4: ¿Auto generado? | L4: ¿Calculado? | M4: ¿Obligatorio? | N4: ¿Sensible? | O4: ¿Identifica al registro? | P4: Descripción | Q4: =A20 -> enviar notificacion | R4: =A21 -> consultar notificaciones | S4: =A22 -> marcar leidas | T4: =#REF! -> #REF!
A5: id | B5: uuid | C5: 36 | D5: 36 | E5: - | F5: - | G5: - | H5: UUID | I5: - | K5: Si | L5: No | M5: Si | N5: No | O5: Si | P5: ID notificación
A6: tipo | B6: enum | C6: - | D6: - | E6: - | F6: - | G6: - | H6: INFO|WARNING | J6: Categoría de alerta | K6: No | L6: No | M6: Si | N6: No | O6: No | P6: Tipo alerta
A7: titulo | B7: alfanumerico | C7: 1 | D7: 150 | E7: - | F7: - | G7: - | H7: Texto | I7: - | K7: No | L7: No | M7: Si | N7: No | O7: No | P7: Asunto
A8: mensaje | B8: alfanumerico | C8: 1 | D8: 500 | E8: - | F8: - | G8: - | H8: Texto | I8: - | K8: No | L8: No | M8: Si | N8: No | O8: No | P8: Cuerpo mensaje
A9: link | B9: alfanumerico | C9: - | D9: - | E9: - | F9: URL | G9: - | I9: - | J9: Destino al hacer clic | K9: No | L9: No | M9: No | N9: No | O9: No | P9: Enlace acción
A10: lectura | B10: boolean | C10: - | D10: - | E10: - | F10: - | G10: - | H10: True/False | I10: False | J10: Estado de lectura | K10: No | L10: No | M10: Si | N10: No | O10: No | P10: ¿Leída?
A11: fecha creacion | B11: fecha | C11: - | D11: - | E11: - | F11: - | G11: - | H11: Date | I11: Now | K11: Si | L11: No | M11: Si | N11: No | O11: No | P11: Fecha recibo
A12: usuario | B12: usuario | C12: - | D12: - | E12: - | F12: - | G12: - | H12: UUID | I12: - | J12: Destinatario | K12: No | L12: No | M12: Si | N12: No | O12: No | P12: Usuario destino
A18: Responsabilidad | C18: Descripción | G18: Entradas | J18: Salida | O18: Políticas (Reglas de Negocio) | Q18: Excepción
G19: Parámetro | H19: Tipo de dato | I19: Descripción | J19: Tipo de Dato | K19: Descripción | O19: Política | P19: Descripción | Q19: Detalle | R19: ¿Qué hago?
A20: enviar notificacion | C20: Genera una alerta al usuario por evento | G20: Tipo, Link, Título | J20: DB/Socket | K20: Notificación creada | O20: Evento disparador | Q20: Falla envío
A21: consultar notificaciones | C21: Lista buzón de entrada del usuario | G21: ID Usuario | J21: JSON | K21: Buzón | O21: Autenticado | Q21: Cero notificaciones
A22: marcar leidas | C22: Cambia estado a leída | G22: ID Notificación | J22: JSON | K22: Actualizado | O22: Click del usuario | Q22: No encontrado

Sheet Plan de suscripción
A1: <-Volver al inicio
A2: Objeto de Dominio: | B2: ='Listado Objetos de Dominio'!$A$13 -> Plan de suscripción
A3: Descripción: | B3: ='Listado Objetos de Dominio'!$B$13 -> Indica el plan al que el usuario se encuentra inscrito y los beneficios que posee con este
A4: Atributo | B4: Tipo de Dato | C4: Longitud mínima | D4: Longitud máxima | E4: Precisión | F4: Rango Inicial | G4: Rango Final | H4: Formato | I4: Valor por defecto | J4: Regla especial | K4: ¿Auto generado? | L4: ¿Calculado? | M4: ¿Obligatorio? | N4: ¿Sensible? | O4: ¿Identifica al registro? | P4: Descripción | Q4: =#REF! -> #REF! | R4: =A18 -> Consultar | S4: =A20 -> Iniciar pago | T4: =#REF! -> #REF!
A5: id | B5: uuid | C5: 36 | D5: 36 | E5: - | F5: - | G5: - | H5: UUID | I5: - | K5: Si | L5: No | M5: Si | N5: No | O5: Si | P5: ID del plan
A6: name | B6: alfanumerico | C6: 1 | D6: 100 | E6: - | F6: - | G6: - | H6: Texto | I6: - | J6: Nombre único (Básico, Pro...) | K6: No | L6: No | M6: Si | N6: No | O6: No | P6: Nombre del plan
A7: price | B7: numero | C7: - | D7: - | E7: 0 | F7: 0 | G7: - | H7: Integer | I7: - | J7: Costo mensual | K7: No | L7: No | M7: Si | N7: No | O7: No | P7: Precio
A8: requestLimit | B8: numero | C8: - | D8: - | E8: - | F8: - | G8: - | H8: Integer | I8: - | J8: Máx solicitudes/mes | K8: No | L8: No | M8: Si | N8: No | O8: No | P8: Límite pedidos
A9: quotationLimit | B9: numero | C9: - | D9: - | E9: - | F9: - | G9: - | H9: Integer | I9: - | J9: Máx respuestas/mes | K9: No | L9: No | M9: Si | N9: No | O9: No | P9: Límite ofertas
A10: collaboratorLimit | B10: numero | C10: - | D10: - | E10: - | F10: - | G10: - | H10: Integer | I10: - | J10: Máx invitados | K10: No | L10: No | M10: Si | N10: No | O10: No | P10: Límite equipo
Q16: Excepción
Q17: Detalle | R17: ¿Qué hago?
A18: Consultar | C18: Servicio que permite consultar los planes de suscripción disponibles
A19: Actualizar metodo de pago | C19: Servicio que permite cambiar el metodo de pago que posee el usuario
A20: Iniciar pago | C20: Servicio que permite iniciar una transacción de pago mediante un servicio externo (WOMPI)

Sheet Transacción de pago
A1: <-Volver al inicio
A2: Objeto de Dominio: | B2: ='Listado Objetos de Dominio'!$A$13 -> Plan de suscripción
A3: Descripción: | B3: ='Listado Objetos de Dominio'!$B$13 -> Indica el plan al que el usuario se encuentra inscrito y los beneficios que posee con este
A4: Atributo | B4: Tipo de Dato | C4: Longitud mínima | D4: Longitud máxima | E4: Precisión | F4: Rango Inicial | G4: Rango Final | H4: Formato | I4: Valor por defecto | J4: Regla especial | K4: ¿Auto generado? | L4: ¿Calculado? | M4: ¿Obligatorio? | N4: ¿Sensible? | O4: ¿Identifica al registro? | P4: Descripción | Q4: =A19 -> 0 | R4: =A20 -> 0 | S4: =A21 -> 0 | T4: =#REF! -> #REF!
A5: id | B5: uuid | C5: 36 | D5: 36 | E5: - | F5: - | G5: - | H5: UUID | I5: - | K5: Si | L5: No | M5: Si | N5: No | O5: Si | P5: ID transacción
A6: usuario | B6: usuario | C6: - | D6: - | E6: - | F6: - | G6: - | H6: UUID | I6: - | J6: Quien paga | K6: No | L6: No | M6: Si | N6: No | O6: No | P6: ID Usuario
A7: plan | B7: Plan de suscripción | C7: - | D7: - | E7: - | F7: - | G7: - | H7: UUID | I7: - | J7: Plan comprado | K7: No | L7: No | M7: Si | N7: No | O7: No | P7: ID Plan
A8: cantidad | B8: numero | C8: - | D8: - | E8: 0 | F8: 0 | G8: - | H8: Monetario | I8: - | J8: Valor pagado | K8: No | L8: No | M8: Si | N8: No | O8: No | P8: Monto
A9: estado | B9: alfanumerico | C9: - | D9: - | E9: - | F9: - | G9: - | H9: Enum | I9: PENDING | J9: Estado del pago (Wompi) | K9: No | L9: No | M9: Si | N9: No | O9: No | P9: Estado
A10: wompiId | B10: alfanumerico | C10: - | D10: - | E10: - | F10: - | G10: - | H10: Texto | I10: - | J10: ID referencia externa | K10: No | L10: No | M10: No | N10: No | O10: No | P10: Ref Wompi
A11: fecha transaccion | B11: date | C11: - | D11: - | E11: - | F11: - | G11: - | H11: Date | I11: Now | J11: Fecha pago | K11: Si | L11: No | M11: Si | N11: No | O11: No | P11: Fecha registro
Q17: Excepción
G18: Parámetro | H18: Tipo de dato | I18: Descripción | J18: Tipo de Dato | K18: Descripción | O18: Política | P18: Descripción | Q18: Detalle | R18: ¿Qué hago?
